Workbook

Sheet 1.承租人-合并源数据
A1: 序号 | B1: 报表分类 | C1: 标准会计科目 | D1: 2022年 | E1: 2023年 | F1: 2024年 | G1: 最新一期
A2: 1 | B2: 资产负债表 | C2: 流动资产合计 | D2: =SUM(D3,D5,D6,D7,D8,D9,D10,D11,D12,D13,D14,D15,D16,D17,D18,D19,D20,D21,D22) | E2: =SUM(E3,E5,E6,E7,E8,E9,E10,E11,E12,E13,E14,E15,E16,E17,E18,E19,E20,E21,E22) | F2: =SUM(F3,F5,F6,F7,F8,F9,F10,F11,F12,F13,F14,F15,F16,F17,F18,F19,F20,F21,F22) | G2: =SUM(G3,G5,G6,G7,G8,G9,G10,G11,G12,G13,G14,G15,G16,G17,G18,G19,G20,G21,G22)
A3: 2 | C3: 货币资金
A4: 3 | C4: 其中：受限货币资金
A5: 4 | C5: 结算备付金
A6: 5 | C6: 拆出资金
A7: 6 | C7: 交易性金融资产 / 短期投资
A8: 7 | C8: 衍生金融资产
A9: 8 | C9: 应收票据
A10: 9 | C10: 应收账款
A11: 10 | C11: 应收款项融资
A12: 11 | C12: 预付款项
A13: 12 | C13: 应收保费 / 应收分保账款
A14: 13 | C14: 应收利息
... A22: 21 | C22: 其他流动资产
A23: 22 | C23: 非流动资产合计 | D23: =SUM(D24,D25,D26,D27,D28,D29,D30,D31,D32,D34,D35,D36,D37,D38,D39,D40,D41,D42) | E23: =SUM(E24,E25,E26,E27,E28,E29,E30,E31,E32,E34,E35,E36,E37,E38,E39,E40,E41,E42) | F23: =SUM(F24,F25,F26,F27,F28,F29,F30,F31,F32,F34,F35,F36,F37,F38,F39,F40,F41,F42) | G23: =SUM(G24,G25,G26,G27,G28,G29,G30,G31,G32,G34,G35,G36,G37,G38,G39,G40,G41,G42)
A24: 23 | C24: 发放贷款和垫款
A25: 24 | C25: 债权投资 / 持有至到期投资
A26: 25 | C26: 其他债权投资 / 可供出售金融资产
A27: 26 | C27: 长期应收款
A28: 27 | C28: 长期股权投资
A29: 28 | C29: 其他权益工具投资
A30: 29 | C30: 其他非流动金融资产
A31: 30 | C31: 投资性房地产
A32: 31 | C32: 固定资产
A33: 32 | C33: 其中：固定资产清理
A34: 33 | C34: 在建工程
A35: 34 | C35: 生产性生物资产 / 油气资产
... A42: 41 | C42: 其他非流动资产
A43: 42 | C43: 资产总计 | D43: =D2+D23 | E43: =E2+E23 | F43: =F2+F23 | G43: =G2+G23
A44: 43 | C44: 流动负债合计 | D44: =SUM(D45,D46,D47,D48,D49,D50,D51,D52,D53,D54,D55,D56,D57,D60,D61,D62) | E44: =SUM(E45,E46,E47,E48,E49,E50,E51,E52,E53,E54,E55,E56,E57,E60,E61,E62) | F44: =SUM(F45,F46,F47,F48,F49,F50,F51,F52,F53,F54,F55,F56,F57,F60,F61,F62) | G44: =SUM(G45,G46,G47,G48,G49,G50,G51,G52,G53,G54,G55,G56,G57,G60,G61,G62)
A45: 44 | C45: 短期借款
A46: 45 | C46: 向中央银行借款
A47: 46 | C47: 拆入资金 / 吸收存款及同业存放
A48: 47 | C48: 交易性金融负债
A49: 48 | C49: 衍生金融负债
A50: 49 | C50: 应付票据
A51: 50 | C51: 应付账款
A52: 51 | C52: 预收款项
A53: 52 | C53: 合同负债
A54: 53 | C54: 卖出回购金融资产款
A55: 54 | C55: 应付职工薪酬
A56: 55 | C56: 应交税费
... A62: 61 | C62: 其他流动负债
A63: 62 | C63: 非流动负债合计 | D63: =SUM(D64,D65,D68,D69,D70,D71,D72,D73,D74) | E63: =SUM(E64,E65,E68,E69,E70,E71,E72,E73,E74) | F63: =SUM(F64,F65,F68,F69,F70,F71,F72,F73,F74) | G63: =SUM(G64,G65,G68,G69,G70,G71,G72,G73,G74)
A64: 63 | C64: 长期借款
A65: 64 | C65: 应付债券
A66: 65 | C66: 其中：优先股
A67: 66 | C67: 其中：永续债
A68: 67 | C68: 租赁负债
A69: 68 | C69: 长期应付款
A70: 69 | C70: 长期应付职工薪酬
A71: 70 | C71: 预计负债
A72: 71 | C72: 递延收益
A73: 72 | C73: 递延所得税负债
A74: 73 | C74: 其他非流动负债
A75: 74 | C75: 负债合计 | D75: =D44+D63 | E75: =E44+E63 | F75: =F44+F63 | G75: =G44+G63
A76: 75 | C76: 所有者权益合计 | D76: =D88+D89 | E76: =E88+E89 | F76: =F88+F89 | G76: =G88+G89
A77: 76 | C77: 实收资本 (或股本)
A78: 77 | C78: 其他权益工具
A79: 78 | C79: 其中：优先股 (权益类)
A80: 79 | C80: 其中：永续债 (权益类)
A81: 80 | C81: 资本公积
A82: 81 | C82: 减：库存股
A83: 82 | C83: 其他综合收益
A84: 83 | C84: 专项储备
A85: 84 | C85: 盈余公积
A86: 85 | C86: 一般风险准备
A87: 86 | C87: 未分配利润
A88: 87 | C88: 归属于母公司所有者权益合计 | D88: =SUM(D77,D78,D81,D83,D84,D85,D86,D87)-SUM(D82) | E88: =SUM(E77,E78,E81,E83,E84,E85,E86,E87)-SUM(E82) | F88: =SUM(F77,F78,F81,F83,F84,F85,F86,F87)-SUM(F82) | G88: =SUM(G77,G78,G81,G83,G84,G85,G86,G87)-SUM(G82)
A89: 88 | C89: 少数股东权益
A90: 89 | C90: 负债和所有者权益总计 | D90: =D75+D76 | E90: =E75+E76 | F90: =F75+F76 | G90: =G75+G76
A91: 90 | C91: 【配平检查】资产 - (负债+权益) | D91: =D43-D90 | E91: =E43-E90 | F91: =F43-F90 | G91: =G43-G90
A93: 91 | B93: 利润表 | C93: 营业总收入
A94: 92 | C94: 营业收入
A95: 93 | C95: 利息收入 / 手续费及佣金收入
A96: 94 | C96: 营业总成本
A97: 95 | C97: 营业成本
A98: 96 | C98: 利息支出 / 手续费及佣金支出
A99: 97 | C99: 税金及附加
A100: 98 | C100: 销售费用
A101: 99 | C101: 管理费用
A102: 100 | C102: 研发费用
A103: 101 | C103: 财务费用
A104: 102 | C104: 其中：利息费用
A105: 103 | C105: 其中：利息收入
... A114: 112 | C114: 资产处置收益
A115: 113 | C115: 营业利润 | D115: =D93-D96+D106+D107+D111-D112-D113+D114 | E115: =E93-E96+E106+E107+E111-E112-E113+E114 | F115: =F93-F96+F106+F107+F111-F112-F113+F114 | G115: =G93-G96+G106+G107+G111-G112-G113+G114
A116: 114 | C116: 加：营业外收入
A117: 115 | C117: 减：营业外支出
A118: 116 | C118: 利润总额 | D118: =D115+D116-D117 | E118: =E115+E116-E117 | F118: =F115+F116-F117 | G118: =G115+G116-G117
A119: 117 | C119: 减：所得税费用
A120: 118 | C120: 净利润 | D120: =D118-D119 | E120: =E118-E119 | F120: =F118-F119 | G120: =G118-G119
A121: 119 | C121: 归属于母公司所有者的净利润
A122: 120 | C122: 少数股东损益
A123: 121 | C123: 综合收益总额
A124: 122 | C124: 【利润勾稽】净利润 - (归母+少数) | D124: =D120-(D121+D122) | E124: =E120-(E121+E122) | F124: =F120-(F121+F122) | G124: =G120-(G121+G122)
A126: 123 | B126: 现金流量表 | C126: 经营活动产生的现金流量：
A127: 124 | C127: 销售商品、提供劳务收到的现金
A128: 125 | C128: 客户存款和同业存放款项净增加额
...

Sheet 2.承租人-本部源数据
A1: 序号 | B1: 报表分类 | C1: 标准会计科目 | D1: 2022年 | E1: 2023年 | F1: 2024年 | G1: 最新一期
A2: 1 | B2: 资产负债表 | C2: 流动资产合计 | D2: =SUM(D3,D5,D6,D7,D8,D9,D10,D11,D12,D13,D14,D15,D16,D17,D18,D19,D20,D21,D22) | E2: =SUM(E3,E5,E6,E7,E8,E9,E10,E11,E12,E13,E14,E15,E16,E17,E18,E19,E20,E21,E22) | F2: =SUM(F3,F5,F6,F7,F8,F9,F10,F11,F12,F13,F14,F15,F16,F17,F18,F19,F20,F21,F22) | G2: =SUM(G3,G5,G6,G7,G8,G9,G10,G11,G12,G13,G14,G15,G16,G17,G18,G19,G20,G21,G22)
A3: 2 | C3: 货币资金
A4: 3 | C4: 其中：受限货币资金
A5: 4 | C5: 结算备付金
A6: 5 | C6: 拆出资金
A7: 6 | C7: 交易性金融资产 / 短期投资
A8: 7 | C8: 衍生金融资产
A9: 8 | C9: 应收票据
A10: 9 | C10: 应收账款
A11: 10 | C11: 应收款项融资
A12: 11 | C12: 预付款项
A13: 12 | C13: 应收保费 / 应收分保账款
A14: 13 | C14: 应收利息
... A22: 21 | C22: 其他流动资产
A23: 22 | C23: 非流动资产合计 | D23: =SUM(D24,D25,D26,D27,D28,D29,D30,D31,D32,D34,D35,D36,D37,D38,D39,D40,D41,D42) | E23: =SUM(E24,E25,E26,E27,E28,E29,E30,E31,E32,E34,E35,E36,E37,E38,E39,E40,E41,E42) | F23: =SUM(F24,F25,F26,F27,F28,F29,F30,F31,F32,F34,F35,F36,F37,F38,F39,F40,F41,F42) | G23: =SUM(G24,G25,G26,G27,G28,G29,G30,G31,G32,G34,G35,G36,G37,G38,G39,G40,G41,G42)
A24: 23 | C24: 发放贷款和垫款
A25: 24 | C25: 债权投资 / 持有至到期投资
A26: 25 | C26: 其他债权投资 / 可供出售金融资产
A27: 26 | C27: 长期应收款
A28: 27 | C28: 长期股权投资
A29: 28 | C29: 其他权益工具投资
A30: 29 | C30: 其他非流动金融资产
A31: 30 | C31: 投资性房地产
A32: 31 | C32: 固定资产
A33: 32 | C33: 其中：固定资产清理
A34: 33 | C34: 在建工程
A35: 34 | C35: 生产性生物资产 / 油气资产
... A42: 41 | C42: 其他非流动资产
A43: 42 | C43: 资产总计 | D43: =D2+D23 | E43: =E2+E23 | F43: =F2+F23 | G43: =G2+G23
A44: 43 | C44: 流动负债合计 | D44: =SUM(D45,D46,D47,D48,D49,D50,D51,D52,D53,D54,D55,D56,D57,D60,D61,D62) | E44: =SUM(E45,E46,E47,E48,E49,E50,E51,E52,E53,E54,E55,E56,E57,E60,E61,E62) | F44: =SUM(F45,F46,F47,F48,F49,F50,F51,F52,F53,F54,F55,F56,F57,F60,F61,F62) | G44: =SUM(G45,G46,G47,G48,G49,G50,G51,G52,G53,G54,G55,G56,G57,G60,G61,G62)
A45: 44 | C45: 短期借款
A46: 45 | C46: 向中央银行借款
A47: 46 | C47: 拆入资金 / 吸收存款及同业存放
A48: 47 | C48: 交易性金融负债
A49: 48 | C49: 衍生金融负债
A50: 49 | C50: 应付票据
A51: 50 | C51: 应付账款
A52: 51 | C52: 预收款项
A53: 52 | C53: 合同负债
A54: 53 | C54: 卖出回购金融资产款
A55: 54 | C55: 应付职工薪酬
A56: 55 | C56: 应交税费
... A62: 61 | C62: 其他流动负债
A63: 62 | C63: 非流动负债合计 | D63: =SUM(D64,D65,D68,D69,D70,D71,D72,D73,D74) | E63: =SUM(E64,E65,E68,E69,E70,E71,E72,E73,E74) | F63: =SUM(F64,F65,F68,F69,F70,F71,F72,F73,F74) | G63: =SUM(G64,G65,G68,G69,G70,G71,G72,G73,G74)
A64: 63 | C64: 长期借款
A65: 64 | C65: 应付债券
A66: 65 | C66: 其中：优先股
A67: 66 | C67: 其中：永续债
A68: 67 | C68: 租赁负债
A69: 68 | C69: 长期应付款
A70: 69 | C70: 长期应付职工薪酬
A71: 70 | C71: 预计负债
A72: 71 | C72: 递延收益
A73: 72 | C73: 递延所得税负债
A74: 73 | C74: 其他非流动负债
A75: 74 | C75: 负债合计 | D75: =D44+D63 | E75: =E44+E63 | F75: =F44+F63 | G75: =G44+G63
A76: 75 | C76: 所有者权益合计 | D76: =D88+D89 | E76: =E88+E89 | F76: =F88+F89 | G76: =G88+G89
A77: 76 | C77: 实收资本 (或股本)
A78: 77 | C78: 其他权益工具
A79: 78 | C79: 其中：优先股 (权益类)
A80: 79 | C80: 其中：永续债 (权益类)
A81: 80 | C81: 资本公积
A82: 81 | C82: 减：库存股
A83: 82 | C83: 其他综合收益
A84: 83 | C84: 专项储备
A85: 84 | C85: 盈余公积
A86: 85 | C86: 一般风险准备
A87: 86 | C87: 未分配利润
A88: 87 | C88: 归属于母公司所有者权益合计 | D88: =SUM(D77,D78,D81,D83,D84,D85,D86,D87)-SUM(D82) | E88: =SUM(E77,E78,E81,E83,E84,E85,E86,E87)-SUM(E82) | F88: =SUM(F77,F78,F81,F83,F84,F85,F86,F87)-SUM(F82) | G88: =SUM(G77,G78,G81,G83,G84,G85,G86,G87)-SUM(G82)
A89: 88 | C89: 少数股东权益
A90: 89 | C90: 负债和所有者权益总计 | D90: =D75+D76 | E90: =E75+E76 | F90: =F75+F76 | G90: =G75+G76
A91: 90 | C91: 【配平检查】资产 - (负债+权益) | D91: =D43-D90 | E91: =E43-E90 | F91: =F43-F90 | G91: =G43-G90
A93: 91 | B93: 利润表 | C93: 营业总收入
A94: 92 | C94: 营业收入
A95: 93 | C95: 利息收入 / 手续费及佣金收入
A96: 94 | C96: 营业总成本
A97: 95 | C97: 营业成本
A98: 96 | C98: 利息支出 / 手续费及佣金支出
A99: 97 | C99: 税金及附加
A100: 98 | C100: 销售费用
A101: 99 | C101: 管理费用
A102: 100 | C102: 研发费用
A103: 101 | C103: 财务费用
A104: 102 | C104: 其中：利息费用
A105: 103 | C105: 其中：利息收入
... A114: 112 | C114: 资产处置收益
A115: 113 | C115: 营业利润 | D115: =D93-D96+D106+D107+D111-D112-D113+D114 | E115: =E93-E96+E106+E107+E111-E112-E113+E114 | F115: =F93-F96+F106+F107+F111-F112-F113+F114 | G115: =G93-G96+G106+G107+G111-G112-G113+G114
A116: 114 | C116: 加：营业外收入
A117: 115 | C117: 减：营业外支出
A118: 116 | C118: 利润总额 | D118: =D115+D116-D117 | E118: =E115+E116-E117 | F118: =F115+F116-F117 | G118: =G115+G116-G117
A119: 117 | C119: 减：所得税费用
A120: 118 | C120: 净利润 | D120: =D118-D119 | E120: =E118-E119 | F120: =F118-F119 | G120: =G118-G119
A121: 119 | C121: 归属于母公司所有者的净利润
A122: 120 | C122: 少数股东损益
A123: 121 | C123: 综合收益总额
A124: 122 | C124: 【利润勾稽】净利润 - (归母+少数) | D124: =D120-(D121+D122) | E124: =E120-(E121+E122) | F124: =F120-(F121+F122) | G124: =G120-(G121+G122)
A126: 123 | B126: 现金流量表 | C126: 经营活动产生的现金流量：
A127: 124 | C127: 销售商品、提供劳务收到的现金
A128: 125 | C128: 客户存款和同业存放款项净增加额
...

Sheet 3.承租人-财务分析
A1: 分析板块 | B1: 财务分析科目 | C1: 合并口径 (单位:万元) | G1: 本部口径 (单位:万元)
C2: 2022年 | D2: 2023年 | E2: 2024年 | F2: 最新一期 | G2: 2022年 | H2: 2023年 | I2: 2024年 | J2: 最新一期
A3: 资产 | B3: 总资产 | C3: ='1.承租人-合并源数据'!D43/10000 | D3: ='1.承租人-合并源数据'!E43/10000 | E3: ='1.承租人-合并源数据'!F43/10000 | F3: ='1.承租人-合并源数据'!G43/10000 | G3: ='2.承租人-本部源数据'!D43/10000 | H3: ='2.承租人-本部源数据'!E43/10000 | I3: ='2.承租人-本部源数据'!F43/10000 | J3: ='2.承租人-本部源数据'!G43/10000
B4: 流动资产 | C4: ='1.承租人-合并源数据'!D2/10000 | D4: ='1.承租人-合并源数据'!E2/10000 | E4: ='1.承租人-合并源数据'!F2/10000 | F4: ='1.承租人-合并源数据'!G2/10000 | G4: ='2.承租人-本部源数据'!D2/10000 | H4: ='2.承租人-本部源数据'!E2/10000 | I4: ='2.承租人-本部源数据'!F2/10000 | J4: ='2.承租人-本部源数据'!G2/10000
B5: 货币资金 | C5: ='1.承租人-合并源数据'!D3/10000 | D5: ='1.承租人-合并源数据'!E3/10000 | E5: ='1.承租人-合并源数据'!F3/10000 | F5: ='1.承租人-合并源数据'!G3/10000 | G5: ='2.承租人-本部源数据'!D3/10000 | H5: ='2.承租人-本部源数据'!E3/10000 | I5: ='2.承租人-本部源数据'!F3/10000 | J5: ='2.承租人-本部源数据'!G3/10000
B6: 应收帐款 | C6: ='1.承租人-合并源数据'!D10/10000 | D6: ='1.承租人-合并源数据'!E10/10000 | E6: ='1.承租人-合并源数据'!F10/10000 | F6: ='1.承租人-合并源数据'!G10/10000 | G6: ='2.承租人-本部源数据'!D10/10000 | H6: ='2.承租人-本部源数据'!E10/10000 | I6: ='2.承租人-本部源数据'!F10/10000 | J6: ='2.承租人-本部源数据'!G10/10000
B7: 其他应收款 | C7: ='1.承租人-合并源数据'!D16/10000 | D7: ='1.承租人-合并源数据'!E16/10000 | E7: ='1.承租人-合并源数据'!F16/10000 | F7: ='1.承租人-合并源数据'!G16/10000 | G7: ='2.承租人-本部源数据'!D16/10000 | H7: ='2.承租人-本部源数据'!E16/10000 | I7: ='2.承租人-本部源数据'!F16/10000 | J7: ='2.承租人-本部源数据'!G16/10000
B8: 预付帐款 | C8: ='1.承租人-合并源数据'!D12/10000 | D8: ='1.承租人-合并源数据'!E12/10000 | E8: ='1.承租人-合并源数据'!F12/10000 | F8: ='1.承租人-合并源数据'!G12/10000 | G8: ='2.承租人-本部源数据'!D12/10000 | H8: ='2.承租人-本部源数据'!E12/10000 | I8: ='2.承租人-本部源数据'!F12/10000 | J8: ='2.承租人-本部源数据'!G12/10000
B9: 存货 | C9: ='1.承租人-合并源数据'!D18/10000 | D9: ='1.承租人-合并源数据'!E18/10000 | E9: ='1.承租人-合并源数据'!F18/10000 | F9: ='1.承租人-合并源数据'!G18/10000 | G9: ='2.承租人-本部源数据'!D18/10000 | H9: ='2.承租人-本部源数据'!E18/10000 | I9: ='2.承租人-本部源数据'!F18/10000 | J9: ='2.承租人-本部源数据'!G18/10000
B10: 其他流动资产 | C10: ='1.承租人-合并源数据'!D22/10000 | D10: ='1.承租人-合并源数据'!E22/10000 | E10: ='1.承租人-合并源数据'!F22/10000 | F10: ='1.承租人-合并源数据'!G22/10000 | G10: ='2.承租人-本部源数据'!D22/10000 | H10: ='2.承租人-本部源数据'!E22/10000 | I10: ='2.承租人-本部源数据'!F22/10000 | J10: ='2.承租人-本部源数据'!G22/10000
B11: 持有至到期投资 | C11: ='1.承租人-合并源数据'!D25/10000 | D11: ='1.承租人-合并源数据'!E25/10000 | E11: ='1.承租人-合并源数据'!F25/10000 | F11: ='1.承租人-合并源数据'!G25/10000 | G11: ='2.承租人-本部源数据'!D25/10000 | H11: ='2.承租人-本部源数据'!E25/10000 | I11: ='2.承租人-本部源数据'!F25/10000 | J11: ='2.承租人-本部源数据'!G25/10000
B12: 长期股权投资 | C12: ='1.承租人-合并源数据'!D28/10000 | D12: ='1.承租人-合并源数据'!E28/10000 | E12: ='1.承租人-合并源数据'!F28/10000 | F12: ='1.承租人-合并源数据'!G28/10000 | G12: ='2.承租人-本部源数据'!D28/10000 | H12: ='2.承租人-本部源数据'!E28/10000 | I12: ='2.承租人-本部源数据'!F28/10000 | J12: ='2.承租人-本部源数据'!G28/10000
B13: 投资性房地产 | C13: ='1.承租人-合并源数据'!D31/10000 | D13: ='1.承租人-合并源数据'!E31/10000 | E13: ='1.承租人-合并源数据'!F31/10000 | F13: ='1.承租人-合并源数据'!G31/10000 | G13: ='2.承租人-本部源数据'!D31/10000 | H13: ='2.承租人-本部源数据'!E31/10000 | I13: ='2.承租人-本部源数据'!F31/10000 | J13: ='2.承租人-本部源数据'!G31/10000
B14: 固定资产 | C14: ='1.承租人-合并源数据'!D32/10000 | D14: ='1.承租人-合并源数据'!E32/10000 | E14: ='1.承租人-合并源数据'!F32/10000 | F14: ='1.承租人-合并源数据'!G32/10000 | G14: ='2.承租人-本部源数据'!D32/10000 | H14: ='2.承租人-本部源数据'!E32/10000 | I14: ='2.承租人-本部源数据'!F32/10000 | J14: ='2.承租人-本部源数据'!G32/10000
B15: 其中：本期新增折旧
B16: 在建工程 | C16: ='1.承租人-合并源数据'!D34/10000 | D16: ='1.承租人-合并源数据'!E34/10000 | E16: ='1.承租人-合并源数据'!F34/10000 | F16: ='1.承租人-合并源数据'!G34/10000 | G16: ='2.承租人-本部源数据'!D34/10000 | H16: ='2.承租人-本部源数据'!E34/10000 | I16: ='2.承租人-本部源数据'!F34/10000 | J16: ='2.承租人-本部源数据'!G34/10000
B17: 无形资产 | C17: ='1.承租人-合并源数据'!D37/10000 | D17: ='1.承租人-合并源数据'!E37/10000 | E17: ='1.承租人-合并源数据'!F37/10000 | F17: ='1.承租人-合并源数据'!G37/10000 | G17: ='2.承租人-本部源数据'!D37/10000 | H17: ='2.承租人-本部源数据'!E37/10000 | I17: ='2.承租人-本部源数据'!F37/10000 | J17: ='2.承租人-本部源数据'!G37/10000
B18: 其中：本期新增摊销
B19: 长期待摊费用 | C19: ='1.承租人-合并源数据'!D40/10000 | D19: ='1.承租人-合并源数据'!E40/10000 | E19: ='1.承租人-合并源数据'!F40/10000 | F19: ='1.承租人-合并源数据'!G40/10000 | G19: ='2.承租人-本部源数据'!D40/10000 | H19: ='2.承租人-本部源数据'!E40/10000 | I19: ='2.承租人-本部源数据'!F40/10000 | J19: ='2.承租人-本部源数据'!G40/10000
B20: 其中：本期新增摊销(长待)
B21: 递延所得税资产 | C21: ='1.承租人-合并源数据'!D41/10000 | D21: ='1.承租人-合并源数据'!E41/10000 | E21: ='1.承租人-合并源数据'!F41/10000 | F21: ='1.承租人-合并源数据'!G41/10000 | G21: ='2.承租人-本部源数据'!D41/10000 | H21: ='2.承租人-本部源数据'!E41/10000 | I21: ='2.承租人-本部源数据'!F41/10000 | J21: ='2.承租人-本部源数据'!G41/10000
B22: 其他非流动资产 | C22: ='1.承租人-合并源数据'!D42/10000 | D22: ='1.承租人-合并源数据'!E42/10000 | E22: ='1.承租人-合并源数据'!F42/10000 | F22: ='1.承租人-合并源数据'!G42/10000 | G22: ='2.承租人-本部源数据'!D42/10000 | H22: ='2.承租人-本部源数据'!E42/10000 | I22: ='2.承租人-本部源数据'!F42/10000 | J22: ='2.承租人-本部源数据'!G42/10000
A23: 负债 | B23: 总负债 | C23: ='1.承租人-合并源数据'!D75/10000 | D23: ='1.承租人-合并源数据'!E75/10000 | E23: ='1.承租人-合并源数据'!F75/10000 | F23: ='1.承租人-合并源数据'!G75/10000 | G23: ='2.承租人-本部源数据'!D75/10000 | H23: ='2.承租人-本部源数据'!E75/10000 | I23: ='2.承租人-本部源数据'!F75/10000 | J23: ='2.承租人-本部源数据'!G75/10000
B24: 流动负债 | C24: ='1.承租人-合并源数据'!D44/10000 | D24: ='1.承租人-合并源数据'!E44/10000 | E24: ='1.承租人-合并源数据'!F44/10000 | F24: ='1.承租人-合并源数据'!G44/10000 | G24: ='2.承租人-本部源数据'!D44/10000 | H24: ='2.承租人-本部源数据'!E44/10000 | I24: ='2.承租人-本部源数据'!F44/10000 | J24: ='2.承租人-本部源数据'!G44/10000
B25: 短期借款 | C25: ='1.承租人-合并源数据'!D45/10000 | D25: ='1.承租人-合并源数据'!E45/10000 | E25: ='1.承租人-合并源数据'!F45/10000 | F25: ='1.承租人-合并源数据'!G45/10000 | G25: ='2.承租人-本部源数据'!D45/10000 | H25: ='2.承租人-本部源数据'!E45/10000 | I25: ='2.承租人-本部源数据'!F45/10000 | J25: ='2.承租人-本部源数据'!G45/10000
B26: 应付账款 | C26: ='1.承租人-合并源数据'!D51/10000 | D26: ='1.承租人-合并源数据'!E51/10000 | E26: ='1.承租人-合并源数据'!F51/10000 | F26: ='1.承租人-合并源数据'!G51/10000 | G26: ='2.承租人-本部源数据'!D51/10000 | H26: ='2.承租人-本部源数据'!E51/10000 | I26: ='2.承租人-本部源数据'!F51/10000 | J26: ='2.承租人-本部源数据'!G51/10000
B27: 预收账款 | C27: ='1.承租人-合并源数据'!D52/10000 | D27: ='1.承租人-合并源数据'!E52/10000 | E27: ='1.承租人-合并源数据'!F52/10000 | F27: ='1.承租人-合并源数据'!G52/10000 | G27: ='2.承租人-本部源数据'!D52/10000 | H27: ='2.承租人-本部源数据'!E52/10000 | I27: ='2.承租人-本部源数据'!F52/10000 | J27: ='2.承租人-本部源数据'!G52/10000
B28: 应付职工薪酬 | C28: ='1.承租人-合并源数据'!D55/10000 | D28: ='1.承租人-合并源数据'!E55/10000 | E28: ='1.承租人-合并源数据'!F55/10000 | F28: ='1.承租人-合并源数据'!G55/10000 | G28: ='2.承租人-本部源数据'!D55/10000 | H28: ='2.承租人-本部源数据'!E55/10000 | I28: ='2.承租人-本部源数据'!F55/10000 | J28: ='2.承租人-本部源数据'!G55/10000
B29: 应交税费 | C29: ='1.承租人-合并源数据'!D56/10000 | D29: ='1.承租人-合并源数据'!E56/10000 | E29: ='1.承租人-合并源数据'!F56/10000 | F29: ='1.承租人-合并源数据'!G56/10000 | G29: ='2.承租人-本部源数据'!D56/10000 | H29: ='2.承租人-本部源数据'!E56/10000 | I29: ='2.承租人-本部源数据'!F56/10000 | J29: ='2.承租人-本部源数据'!G56/10000
B30: 其他应付款 | C30: ='1.承租人-合并源数据'!D57/10000 | D30: ='1.承租人-合并源数据'!E57/10000 | E30: ='1.承租人-合并源数据'!F57/10000 | F30: ='1.承租人-合并源数据'!G57/10000 | G30: ='2.承租人-本部源数据'!D57/10000 | H30: ='2.承租人-本部源数据'!E57/10000 | I30: ='2.承租人-本部源数据'!F57/10000 | J30: ='2.承租人-本部源数据'!G57/10000
B31: 一年内的到期的非流动负债 | C31: ='1.承租人-合并源数据'!D61/10000 | D31: ='1.承租人-合并源数据'!E61/10000 | E31: ='1.承租人-合并源数据'!F61/10000 | F31: ='1.承租人-合并源数据'!G61/10000 | G31: ='2.承租人-本部源数据'!D61/10000 | H31: ='2.承租人-本部源数据'!E61/10000 | I31: ='2.承租人-本部源数据'!F61/10000 | J31: ='2.承租人-本部源数据'!G61/10000
B32: 长期借款 | C32: ='1.承租人-合并源数据'!D64/10000 | D32: ='1.承租人-合并源数据'!E64/10000 | E32: ='1.承租人-合并源数据'!F64/10000 | F32: ='1.承租人-合并源数据'!G64/10000 | G32: ='2.承租人-本部源数据'!D64/10000 | H32: ='2.承租人-本部源数据'!E64/10000 | I32: ='2.承租人-本部源数据'!F64/10000 | J32: ='2.承租人-本部源数据'!G64/10000
B33: 长期应付款 | C33: ='1.承租人-合并源数据'!D69/10000 | D33: ='1.承租人-合并源数据'!E69/10000 | E33: ='1.承租人-合并源数据'!F69/10000 | F33: ='1.承租人-合并源数据'!G69/10000 | G33: ='2.承租人-本部源数据'!D69/10000 | H33: ='2.承租人-本部源数据'!E69/10000 | I33: ='2.承租人-本部源数据'!F69/10000 | J33: ='2.承租人-本部源数据'!G69/10000
B34: 应付债券 | C34: ='1.承租人-合并源数据'!D65/10000 | D34: ='1.承租人-合并源数据'!E65/10000 | E34: ='1.承租人-合并源数据'!F65/10000 | F34: ='1.承租人-合并源数据'!G65/10000 | G34: ='2.承租人-本部源数据'!D65/10000 | H34: ='2.承租人-本部源数据'!E65/10000 | I34: ='2.承租人-本部源数据'!F65/10000 | J34: ='2.承租人-本部源数据'!G65/10000
A35: 权益 | B35: 净资产 | C35: ='1.承租人-合并源数据'!D76/10000 | D35: ='1.承租人-合并源数据'!E76/10000 | E35: ='1.承租人-合并源数据'!F76/10000 | F35: ='1.承租人-合并源数据'!G76/10000 | G35: ='2.承租人-本部源数据'!D76/10000 | H35: ='2.承租人-本部源数据'!E76/10000 | I35: ='2.承租人-本部源数据'!F76/10000 | J35: ='2.承租人-本部源数据'!G76/10000
B36: 实收资本 | C36: ='1.承租人-合并源数据'!D77/10000 | D36: ='1.承租人-合并源数据'!E77/10000 | E36: ='1.承租人-合并源数据'!F77/10000 | F36: ='1.承租人-合并源数据'!G77/10000 | G36: ='2.承租人-本部源数据'!D77/10000 | H36: ='2.承租人-本部源数据'!E77/10000 | I36: ='2.承租人-本部源数据'!F77/10000 | J36: ='2.承租人-本部源数据'!G77/10000
B37: 资本公积 | C37: ='1.承租人-合并源数据'!D81/10000 | D37: ='1.承租人-合并源数据'!E81/10000 | E37: ='1.承租人-合并源数据'!F81/10000 | F37: ='1.承租人-合并源数据'!G81/10000 | G37: ='2.承租人-本部源数据'!D81/10000 | H37: ='2.承租人-本部源数据'!E81/10000 | I37: ='2.承租人-本部源数据'!F81/10000 | J37: ='2.承租人-本部源数据'!G81/10000
B38: 盈余公积 | C38: ='1.承租人-合并源数据'!D85/10000 | D38: ='1.承租人-合并源数据'!E85/10000 | E38: ='1.承租人-合并源数据'!F85/10000 | F38: ='1.承租人-合并源数据'!G85/10000 | G38: ='2.承租人-本部源数据'!D85/10000 | H38: ='2.承租人-本部源数据'!E85/10000 | I38: ='2.承租人-本部源数据'!F85/10000 | J38: ='2.承租人-本部源数据'!G85/10000
B39: 未分配利润 | C39: ='1.承租人-合并源数据'!D87/10000 | D39: ='1.承租人-合并源数据'!E87/10000 | E39: ='1.承租人-合并源数据'!F87/10000 | F39: ='1.承租人-合并源数据'!G87/10000 | G39: ='2.承租人-本部源数据'!D87/10000 | H39: ='2.承租人-本部源数据'!E87/10000 | I39: ='2.承租人-本部源数据'!F87/10000 | J39: ='2.承租人-本部源数据'!G87/10000
A40: 盈利能力 | B40: 营业收入 | C40: ='1.承租人-合并源数据'!D94/10000 | D40: ='1.承租人-合并源数据'!E94/10000 | E40: ='1.承租人-合并源数据'!F94/10000 | F40: ='1.承租人-合并源数据'!G94/10000 | G40: ='2.承租人-本部源数据'!D94/10000 | H40: ='2.承租人-本部源数据'!E94/10000 | I40: ='2.承租人-本部源数据'!F94/10000 | J40: ='2.承租人-本部源数据'!G94/10000
B41: 主营业务成本 | C41: ='1.承租人-合并源数据'!D97/10000 | D41: ='1.承租人-合并源数据'!E97/10000 | E41: ='1.承租人-合并源数据'!F97/10000 | F41: ='1.承租人-合并源数据'!G97/10000 | G41: ='2.承租人-本部源数据'!D97/10000 | H41: ='2.承租人-本部源数据'!E97/10000 | I41: ='2.承租人-本部源数据'!F97/10000 | J41: ='2.承租人-本部源数据'!G97/10000
B42: 主营业务利润 | C42: =('1.承租人-合并源数据'!D94 - '1.承租人-合并源数据'!D97)/10000 | D42: =('1.承租人-合并源数据'!E94 - '1.承租人-合并源数据'!E97)/10000 | E42: =('1.承租人-合并源数据'!F94 - '1.承租人-合并源数据'!F97)/10000 | F42: =('1.承租人-合并源数据'!G94 - '1.承租人-合并源数据'!G97)/10000 | G42: =('2.承租人-本部源数据'!D94 - '2.承租人-本部源数据'!D97)/10000 | H42: =('2.承租人-本部源数据'!E94 - '2.承租人-本部源数据'!E97)/10000 | I42: =('2.承租人-本部源数据'!F94 - '2.承租人-本部源数据'!F97)/10000 | J42: =('2.承租人-本部源数据'!G94 - '2.承租人-本部源数据'!G97)/10000
B43: 期间费用 | C43: =('1.承租人-合并源数据'!D100 + '1.承租人-合并源数据'!D101 + '1.承租人-合并源数据'!D102 + '1.承租人-合并源数据'!D103)/10000 | D43: =('1.承租人-合并源数据'!E100 + '1.承租人-合并源数据'!E101 + '1.承租人-合并源数据'!E102 + '1.承租人-合并源数据'!E103)/10000 | E43: =('1.承租人-合并源数据'!F100 + '1.承租人-合并源数据'!F101 + '1.承租人-合并源数据'!F102 + '1.承租人-合并源数据'!F103)/10000 | F43: =('1.承租人-合并源数据'!G100 + '1.承租人-合并源数据'!G101 + '1.承租人-合并源数据'!G102 + '1.承租人-合并源数据'!G103)/10000 | G43: =('2.承租人-本部源数据'!D100 + '2.承租人-本部源数据'!D101 + '2.承租人-本部源数据'!D102 + '2.承租人-本部源数据'!D103)/10000 | H43: =('2.承租人-本部源数据'!E100 + '2.承租人-本部源数据'!E101 + '2.承租人-本部源数据'!E102 + '2.承租人-本部源数据'!E103)/10000 | I43: =('2.承租人-本部源数据'!F100 + '2.承租人-本部源数据'!F101 + '2.承租人-本部源数据'!F102 + '2.承租人-本部源数据'!F103)/10000 | J43: =('2.承租人-本部源数据'!G100 + '2.承租人-本部源数据'!G101 + '2.承租人-本部源数据'!G102 + '2.承租人-本部源数据'!G103)/10000
B44: 股权变动收益 | C44: ='1.承租人-合并源数据'!D107/10000 | D44: ='1.承租人-合并源数据'!E107/10000 | E44: ='1.承租人-合并源数据'!F107/10000 | F44: ='1.承租人-合并源数据'!G107/10000 | G44: ='2.承租人-本部源数据'!D107/10000 | H44: ='2.承租人-本部源数据'!E107/10000 | I44: ='2.承租人-本部源数据'!F107/10000 | J44: ='2.承租人-本部源数据'!G107/10000
B45: 其他收益（政府补助） | C45: ='1.承租人-合并源数据'!D106/10000 | D45: ='1.承租人-合并源数据'!E106/10000 | E45: ='1.承租人-合并源数据'!F106/10000 | F45: ='1.承租人-合并源数据'!G106/10000 | G45: ='2.承租人-本部源数据'!D106/10000 | H45: ='2.承租人-本部源数据'!E106/10000 | I45: ='2.承租人-本部源数据'!F106/10000 | J45: ='2.承租人-本部源数据'!G106/10000
B46: 利润总额 | C46: ='1.承租人-合并源数据'!D118/10000 | D46: ='1.承租人-合并源数据'!E118/10000 | E46: ='1.承租人-合并源数据'!F118/10000 | F46: ='1.承租人-合并源数据'!G118/10000 | G46: ='2.承租人-本部源数据'!D118/10000 | H46: ='2.承租人-本部源数据'!E118/10000 | I46: ='2.承租人-本部源数据'!F118/10000 | J46: ='2.承租人-本部源数据'!G118/10000
B47: 净利润 | C47: ='1.承租人-合并源数据'!D120/10000 | D47: ='1.承租人-合并源数据'!E120/10000 | E47: ='1.承租人-合并源数据'!F120/10000 | F47: ='1.承租人-合并源数据'!G120/10000 | G47: ='2.承租人-本部源数据'!D120/10000 | H47: ='2.承租人-本部源数据'!E120/10000 | I47: ='2.承租人-本部源数据'!F120/10000 | J47: ='2.承租人-本部源数据'!G120/10000
B48: 主营业务利润率 | C48: =IF('1.承租人-合并源数据'!D94=0, 0, ('1.承租人-合并源数据'!D94 - '1.承租人-合并源数据'!D97) / '1.承租人-合并源数据'!D94) | D48: =IF('1.承租人-合并源数据'!E94=0, 0, ('1.承租人-合并源数据'!E94 - '1.承租人-合并源数据'!E97) / '1.承租人-合并源数据'!E94) | E48: =IF('1.承租人-合并源数据'!F94=0, 0, ('1.承租人-合并源数据'!F94 - '1.承租人-合并源数据'!F97) / '1.承租人-合并源数据'!F94) | F48: =IF('1.承租人-合并源数据'!G94=0, 0, ('1.承租人-合并源数据'!G94 - '1.承租人-合并源数据'!G97) / '1.承租人-合并源数据'!G94) | G48: =IF('2.承租人-本部源数据'!D94=0, 0, ('2.承租人-本部源数据'!D94 - '2.承租人-本部源数据'!D97) / '2.承租人-本部源数据'!D94) | H48: =IF('2.承租人-本部源数据'!E94=0, 0, ('2.承租人-本部源数据'!E94 - '2.承租人-本部源数据'!E97) / '2.承租人-本部源数据'!E94) | I48: =IF('2.承租人-本部源数据'!F94=0, 0, ('2.承租人-本部源数据'!F94 - '2.承租人-本部源数据'!F97) / '2.承租人-本部源数据'!F94) | J48: =IF('2.承租人-本部源数据'!G94=0, 0, ('2.承租人-本部源数据'!G94 - '2.承租人-本部源数据'!G97) / '2.承租人-本部源数据'!G94)
B49: 期间费用率 | C49: =IF('1.承租人-合并源数据'!D94=0, 0, ('1.承租人-合并源数据'!D100 + '1.承租人-合并源数据'!D101 + '1.承租人-合并源数据'!D102 + '1.承租人-合并源数据'!D103) / '1.承租人-合并源数据'!D94) | D49: =IF('1.承租人-合并源数据'!E94=0, 0, ('1.承租人-合并源数据'!E100 + '1.承租人-合并源数据'!E101 + '1.承租人-合并源数据'!E102 + '1.承租人-合并源数据'!E103) / '1.承租人-合并源数据'!E94) | E49: =IF('1.承租人-合并源数据'!F94=0, 0, ('1.承租人-合并源数据'!F100 + '1.承租人-合并源数据'!F101 + '1.承租人-合并源数据'!F102 + '1.承租人-合并源数据'!F103) / '1.承租人-合并源数据'!F94) | F49: =IF('1.承租人-合并源数据'!G94=0, 0, ('1.承租人-合并源数据'!G100 + '1.承租人-合并源数据'!G101 + '1.承租人-合并源数据'!G102 + '1.承租人-合并源数据'!G103) / '1.承租人-合并源数据'!G94) | G49: =IF('2.承租人-本部源数据'!D94=0, 0, ('2.承租人-本部源数据'!D100 + '2.承租人-本部源数据'!D101 + '2.承租人-本部源数据'!D102 + '2.承租人-本部源数据'!D103) / '2.承租人-本部源数据'!D94) | H49: =IF('2.承租人-本部源数据'!E94=0, 0, ('2.承租人-本部源数据'!E100 + '2.承租人-本部源数据'!E101 + '2.承租人-本部源数据'!E102 + '2.承租人-本部源数据'!E103) / '2.承租人-本部源数据'!E94) | I49: =IF('2.承租人-本部源数据'!F94=0, 0, ('2.承租人-本部源数据'!F100 + '2.承租人-本部源数据'!F101 + '2.承租人-本部源数据'!F102 + '2.承租人-本部源数据'!F103) / '2.承租人-本部源数据'!F94) | J49: =IF('2.承租人-本部源数据'!G94=0, 0, ('2.承租人-本部源数据'!G100 + '2.承租人-本部源数据'!G101 + '2.承租人-本部源数据'!G102 + '2.承租人-本部源数据'!G103) / '2.承租人-本部源数据'!G94)
B50: 净利率 | C50: =IF('1.承租人-合并源数据'!D94=0, 0, '1.承租人-合并源数据'!D120 / '1.承租人-合并源数据'!D94) | D50: =IF('1.承租人-合并源数据'!E94=0, 0, '1.承租人-合并源数据'!E120 / '1.承租人-合并源数据'!E94) | E50: =IF('1.承租人-合并源数据'!F94=0, 0, '1.承租人-合并源数据'!F120 / '1.承租人-合并源数据'!F94) | F50: =IF('1.承租人-合并源数据'!G94=0, 0, '1.承租人-合并源数据'!G120 / '1.承租人-合并源数据'!G94) | G50: =IF('2.承租人-本部源数据'!D94=0, 0, '2.承租人-本部源数据'!D120 / '2.承租人-本部源数据'!D94) | H50: =IF('2.承租人-本部源数据'!E94=0, 0, '2.承租人-本部源数据'!E120 / '2.承租人-本部源数据'!E94) | I50: =IF('2.承租人-本部源数据'!F94=0, 0, '2.承租人-本部源数据'!F120 / '2.承租人-本部源数据'!F94) | J50: =IF('2.承租人-本部源数据'!G94=0, 0, '2.承租人-本部源数据'!G120 / '2.承租人-本部源数据'!G94)
A51: 营运能力 | B51: 应收账款周转天数 | C51: =IF('1.承租人-合并源数据'!D94=0, 0, 360 * '1.承租人-合并源数据'!D10 / '1.承租人-合并源数据'!D94) | D51: =IF('1.承租人-合并源数据'!E94=0, 0, 360 * '1.承租人-合并源数据'!E10 / '1.承租人-合并源数据'!E94) | E51: =IF('1.承租人-合并源数据'!F94=0, 0, 360 * '1.承租人-合并源数据'!F10 / '1.承租人-合并源数据'!F94) | F51: =IF('1.承租人-合并源数据'!G94=0, 0, 360 * '1.承租人-合并源数据'!G10 / '1.承租人-合并源数据'!G94) | G51: =IF('2.承租人-本部源数据'!D94=0, 0, 360 * '2.承租人-本部源数据'!D10 / '2.承租人-本部源数据'!D94) | H51: =IF('2.承租人-本部源数据'!E94=0, 0, 360 * '2.承租人-本部源数据'!E10 / '2.承租人-本部源数据'!E94) | I51: =IF('2.承租人-本部源数据'!F94=0, 0, 360 * '2.承租人-本部源数据'!F10 / '2.承租人-本部源数据'!F94) | J51: =IF('2.承租人-本部源数据'!G94=0, 0, 360 * '2.承租人-本部源数据'!G10 / '2.承租人-本部源数据'!G94)
B52: 存货周转天数 | C52: =IF('1.承租人-合并源数据'!D97=0, 0, 360 * '1.承租人-合并源数据'!D18 / '1.承租人-合并源数据'!D97) | D52: =IF('1.承租人-合并源数据'!E97=0, 0, 360 * '1.承租人-合并源数据'!E18 / '1.承租人-合并源数据'!E97) | E52: =IF('1.承租人-合并源数据'!F97=0, 0, 360 * '1.承租人-合并源数据'!F18 / '1.承租人-合并源数据'!F97) | F52: =IF('1.承租人-合并源数据'!G97=0, 0, 360 * '1.承租人-合并源数据'!G18 / '1.承租人-合并源数据'!G97) | G52: =IF('2.承租人-本部源数据'!D97=0, 0, 360 * '2.承租人-本部源数据'!D18 / '2.承租人-本部源数据'!D97) | H52: =IF('2.承租人-本部源数据'!E97=0, 0, 360 * '2.承租人-本部源数据'!E18 / '2.承租人-本部源数据'!E97) | I52: =IF('2.承租人-本部源数据'!F97=0, 0, 360 * '2.承租人-本部源数据'!F18 / '2.承租人-本部源数据'!F97) | J52: =IF('2.承租人-本部源数据'!G97=0, 0, 360 * '2.承租人-本部源数据'!G18 / '2.承租人-本部源数据'!G97)
A53: 偿债能力 | B53: 资产负债率 | C53: =IF('1.承租人-合并源数据'!D43=0, 0, '1.承租人-合并源数据'!D75 / '1.承租人-合并源数据'!D43) | D53: =IF('1.承租人-合并源数据'!E43=0, 0, '1.承租人-合并源数据'!E75 / '1.承租人-合并源数据'!E43) | E53: =IF('1.承租人-合并源数据'!F43=0, 0, '1.承租人-合并源数据'!F75 / '1.承租人-合并源数据'!F43) | F53: =IF('1.承租人-合并源数据'!G43=0, 0, '1.承租人-合并源数据'!G75 / '1.承租人-合并源数据'!G43) | G53: =IF('2.承租人-本部源数据'!D43=0, 0, '2.承租人-本部源数据'!D75 / '2.承租人-本部源数据'!D43) | H53: =IF('2.承租人-本部源数据'!E43=0, 0, '2.承租人-本部源数据'!E75 / '2.承租人-本部源数据'!E43) | I53: =IF('2.承租人-本部源数据'!F43=0, 0, '2.承租人-本部源数据'!F75 / '2.承租人-本部源数据'!F43) | J53: =IF('2.承租人-本部源数据'!G43=0, 0, '2.承租人-本部源数据'!G75 / '2.承租人-本部源数据'!G43)
B54: 现金短期有息债务比率 | C54: =IF(('1.承租人-合并源数据'!D45 + '1.承租人-合并源数据'!D50 + '1.承租人-合并源数据'!D61)=0, 0, '1.承租人-合并源数据'!D3 / ('1.承租人-合并源数据'!D45 + '1.承租人-合并源数据'!D50 + '1.承租人-合并源数据'!D61)) | D54: =IF(('1.承租人-合并源数据'!E45 + '1.承租人-合并源数据'!E50 + '1.承租人-合并源数据'!E61)=0, 0, '1.承租人-合并源数据'!E3 / ('1.承租人-合并源数据'!E45 + '1.承租人-合并源数据'!E50 + '1.承租人-合并源数据'!E61)) | E54: =IF(('1.承租人-合并源数据'!F45 + '1.承租人-合并源数据'!F50 + '1.承租人-合并源数据'!F61)=0, 0, '1.承租人-合并源数据'!F3 / ('1.承租人-合并源数据'!F45 + '1.承租人-合并源数据'!F50 + '1.承租人-合并源数据'!F61)) | F54: =IF(('1.承租人-合并源数据'!G45 + '1.承租人-合并源数据'!G50 + '1.承租人-合并源数据'!G61)=0, 0, '1.承租人-合并源数据'!G3 / ('1.承租人-合并源数据'!G45 + '1.承租人-合并源数据'!G50 + '1.承租人-合并源数据'!G61)) | G54: =IF(('2.承租人-本部源数据'!D45 + '2.承租人-本部源数据'!D50 + '2.承租人-本部源数据'!D61)=0, 0, '2.承租人-本部源数据'!D3 / ('2.承租人-本部源数据'!D45 + '2.承租人-本部源数据'!D50 + '2.承租人-本部源数据'!D61)) | H54: =IF(('2.承租人-本部源数据'!E45 + '2.承租人-本部源数据'!E50 + '2.承租人-本部源数据'!E61)=0, 0, '2.承租人-本部源数据'!E3 / ('2.承租人-本部源数据'!E45 + '2.承租人-本部源数据'!E50 + '2.承租人-本部源数据'!E61)) | I54: =IF(('2.承租人-本部源数据'!F45 + '2.承租人-本部源数据'!F50 + '2.承租人-本部源数据'!F61)=0, 0, '2.承租人-本部源数据'!F3 / ('2.承租人-本部源数据'!F45 + '2.承租人-本部源数据'!F50 + '2.承租人-本部源数据'!F61)) | J54: =IF(('2.承租人-本部源数据'!G45 + '2.承租人-本部源数据'!G50 + '2.承租人-本部源数据'!G61)=0, 0, '2.承租人-本部源数据'!G3 / ('2.承租人-本部源数据'!G45 + '2.承租人-本部源数据'!G50 + '2.承租人-本部源数据'!G61))
B55: 付现利息 | C55: ='1.承租人-合并源数据'!D165/10000 | D55: ='1.承租人-合并源数据'!E165/10000 | E55: ='1.承租人-合并源数据'!F165/10000 | F55: ='1.承租人-合并源数据'!G165/10000 | G55: ='2.承租人-本部源数据'!D165/10000 | H55: ='2.承租人-本部源数据'!E165/10000 | I55: ='2.承租人-本部源数据'!F165/10000 | J55: ='2.承租人-本部源数据'!G165/10000
B56: 其中：计入利润表的财务费用 | C56: ='1.承租人-合并源数据'!D104/10000 | D56: ='1.承租人-合并源数据'!E104/10000 | E56: ='1.承租人-合并源数据'!F104/10000 | F56: ='1.承租人-合并源数据'!G104/10000 | G56: ='2.承租人-本部源数据'!D104/10000 | H56: ='2.承租人-本部源数据'!E104/10000 | I56: ='2.承租人-本部源数据'!F104/10000 | J56: ='2.承租人-本部源数据'!G104/10000
B57: EBIT利息倍数 | C57: =IF('1.承租人-合并源数据'!D104=0, "-", ('1.承租人-合并源数据'!D118 + '1.承租人-合并源数据'!D104) / '1.承租人-合并源数据'!D104) | D57: =IF('1.承租人-合并源数据'!E104=0, "-", ('1.承租人-合并源数据'!E118 + '1.承租人-合并源数据'!E104) / '1.承租人-合并源数据'!E104) | E57: =IF('1.承租人-合并源数据'!F104=0, "-", ('1.承租人-合并源数据'!F118 + '1.承租人-合并源数据'!F104) / '1.承租人-合并源数据'!F104) | F57: =IF('1.承租人-合并源数据'!G104=0, "-", ('1.承租人-合并源数据'!G118 + '1.承租人-合并源数据'!G104) / '1.承租人-合并源数据'!G104) | G57: =IF('2.承租人-本部源数据'!D104=0, "-", ('2.承租人-本部源数据'!D118 + '2.承租人-本部源数据'!D104) / '2.承租人-本部源数据'!D104) | H57: =IF('2.承租人-本部源数据'!E104=0, "-", ('2.承租人-本部源数据'!E118 + '2.承租人-本部源数据'!E104) / '2.承租人-本部源数据'!E104) | I57: =IF('2.承租人-本部源数据'!F104=0, "-", ('2.承租人-本部源数据'!F118 + '2.承租人-本部源数据'!F104) / '2.承租人-本部源数据'!F104) | J57: =IF('2.承租人-本部源数据'!G104=0, "-", ('2.承租人-本部源数据'!G118 + '2.承租人-本部源数据'!G104) / '2.承租人-本部源数据'!G104)
B58: EBITDA利息倍数 | C58: =IF('1.承租人-合并源数据'!D104=0, "-", ('1.承租人-合并源数据'!D118 + '1.承租人-合并源数据'!D104 + C15 + C18 + C20) / '1.承租人-合并源数据'!D104) | D58: =IF('1.承租人-合并源数据'!E104=0, "-", ('1.承租人-合并源数据'!E118 + '1.承租人-合并源数据'!E104 + D15 + D18 + D20) / '1.承租人-合并源数据'!E104) | E58: =IF('1.承租人-合并源数据'!F104=0, "-", ('1.承租人-合并源数据'!F118 + '1.承租人-合并源数据'!F104 + E15 + E18 + E20) / '1.承租人-合并源数据'!F104) | F58: =IF('1.承租人-合并源数据'!G104=0, "-", ('1.承租人-合并源数据'!G118 + '1.承租人-合并源数据'!G104 + F15 + F18 + F20) / '1.承租人-合并源数据'!G104) | G58: =IF('2.承租人-本部源数据'!D104=0, "-", ('2.承租人-本部源数据'!D118 + '2.承租人-本部源数据'!D104 + G15 + G18 + G20) / '2.承租人-本部源数据'!D104) | H58: =IF('2.承租人-本部源数据'!E104=0, "-", ('2.承租人-本部源数据'!E118 + '2.承租人-本部源数据'!E104 + H15 + H18 + H20) / '2.承租人-本部源数据'!E104) | I58: =IF('2.承租人-本部源数据'!F104=0, "-", ('2.承租人-本部源数据'!F118 + '2.承租人-本部源数据'!F104 + I15 + I18 + I20) / '2.承租人-本部源数据'!F104) | J58: =IF('2.承租人-本部源数据'!G104=0, "-", ('2.承租人-本部源数据'!G118 + '2.承租人-本部源数据'!G104 + J15 + J18 + J20) / '2.承租人-本部源数据'!G104)
B59: 经营净现金流利息保障倍数 | C59: =IF('1.承租人-合并源数据'!D104=0, "-", '1.承租人-合并源数据'!D142 / '1.承租人-合并源数据'!D104) | D59: =IF('1.承租人-合并源数据'!E104=0, "-", '1.承租人-合并源数据'!E142 / '1.承租人-合并源数据'!E104) | E59: =IF('1.承租人-合并源数据'!F104=0, "-", '1.承租人-合并源数据'!F142 / '1.承租人-合并源数据'!F104) | F59: =IF('1.承租人-合并源数据'!G104=0, "-", '1.承租人-合并源数据'!G142 / '1.承租人-合并源数据'!G104) | G59: =IF('2.承租人-本部源数据'!D104=0, "-", '2.承租人-本部源数据'!D142 / '2.承租人-本部源数据'!D104) | H59: =IF('2.承租人-本部源数据'!E104=0, "-", '2.承租人-本部源数据'!E142 / '2.承租人-本部源数据'!E104) | I59: =IF('2.承租人-本部源数据'!F104=0, "-", '2.承租人-本部源数据'!F142 / '2.承租人-本部源数据'!F104) | J59: =IF('2.承租人-本部源数据'!G104=0, "-", '2.承租人-本部源数据'!G142 / '2.承租人-本部源数据'!G104)
A60: 现金流 | B60: 经营活动净现金流量 | C60: ='1.承租人-合并源数据'!D142/10000 | D60: ='1.承租人-合并源数据'!E142/10000 | E60: ='1.承租人-合并源数据'!F142/10000 | F60: ='1.承租人-合并源数据'!G142/10000 | G60: ='2.承租人-本部源数据'!D142/10000 | H60: ='2.承租人-本部源数据'!E142/10000 | I60: ='2.承租人-本部源数据'!F142/10000 | J60: ='2.承租人-本部源数据'!G142/10000
B61: 其中，销售商品提供劳务收到的现金 | C61: ='1.承租人-合并源数据'!D127/10000 | D61: ='1.承租人-合并源数据'!E127/10000 | E61: ='1.承租人-合并源数据'!F127/10000 | F61: ='1.承租人-合并源数据'!G127/10000 | G61: ='2.承租人-本部源数据'!D127/10000 | H61: ='2.承租人-本部源数据'!E127/10000 | I61: ='2.承租人-本部源数据'!F127/10000 | J61: ='2.承租人-本部源数据'!G127/10000
B62: 收现比 | C62: =IF('1.承租人-合并源数据'!D94=0, 0, '1.承租人-合并源数据'!D127 / '1.承租人-合并源数据'!D94) | D62: =IF('1.承租人-合并源数据'!E94=0, 0, '1.承租人-合并源数据'!E127 / '1.承租人-合并源数据'!E94) | E62: =IF('1.承租人-合并源数据'!F94=0, 0, '1.承租人-合并源数据'!F127 / '1.承租人-合并源数据'!F94) | F62: =IF('1.承租人-合并源数据'!G94=0, 0, '1.承租人-合并源数据'!G127 / '1.承租人-合并源数据'!G94) | G62: =IF('2.承租人-本部源数据'!D94=0, 0, '2.承租人-本部源数据'!D127 / '2.承租人-本部源数据'!D94) | H62: =IF('2.承租人-本部源数据'!E94=0, 0, '2.承租人-本部源数据'!E127 / '2.承租人-本部源数据'!E94) | I62: =IF('2.承租人-本部源数据'!F94=0, 0, '2.承租人-本部源数据'!F127 / '2.承租人-本部源数据'!F94) | J62: =IF('2.承租人-本部源数据'!G94=0, 0, '2.承租人-本部源数据'!G127 / '2.承租人-本部源数据'!G94)
B63: 投资活动净现金流 | C63: ='1.承租人-合并源数据'!D156/10000 | D63: ='1.承租人-合并源数据'!E156/10000 | E63: ='1.承租人-合并源数据'!F156/10000 | F63: ='1.承租人-合并源数据'!G156/10000 | G63: ='2.承租人-本部源数据'!D156/10000 | H63: ='2.承租人-本部源数据'!E156/10000 | I63: ='2.承租人-本部源数据'!F156/10000 | J63: ='2.承租人-本部源数据'!G156/10000
B64: 筹资活动净现金流 | C64: ='1.承租人-合并源数据'!D169/10000 | D64: ='1.承租人-合并源数据'!E169/10000 | E64: ='1.承租人-合并源数据'!F169/10000 | F64: ='1.承租人-合并源数据'!G169/10000 | G64: ='2.承租人-本部源数据'!D169/10000 | H64: ='2.承租人-本部源数据'!E169/10000 | I64: ='2.承租人-本部源数据'!F169/10000 | J64: ='2.承租人-本部源数据'!G169/10000
B65: 净现金流 | C65: ='1.承租人-合并源数据'!D171/10000 | D65: ='1.承租人-合并源数据'!E171/10000 | E65: ='1.承租人-合并源数据'!F171/10000 | F65: ='1.承租人-合并源数据'!G171/10000 | G65: ='2.承租人-本部源数据'!D171/10000 | H65: ='2.承租人-本部源数据'!E171/10000 | I65: ='2.承租人-本部源数据'!F171/10000 | J65: ='2.承租人-本部源数据'!G171/10000

Sheet 4.担保人-合并源数据
A1: 序号 | B1: 报表分类 | C1: 标准会计科目 | D1: 2022年 | E1: 2023年 | F1: 2024年 | G1: 最新一期
A2: 1 | B2: 资产负债表 | C2: 流动资产合计 | D2: =SUM(D3,D5,D6,D7,D8,D9,D10,D11,D12,D13,D14,D15,D16,D17,D18,D19,D20,D21,D22) | E2: =SUM(E3,E5,E6,E7,E8,E9,E10,E11,E12,E13,E14,E15,E16,E17,E18,E19,E20,E21,E22) | F2: =SUM(F3,F5,F6,F7,F8,F9,F10,F11,F12,F13,F14,F15,F16,F17,F18,F19,F20,F21,F22) | G2: =SUM(G3,G5,G6,G7,G8,G9,G10,G11,G12,G13,G14,G15,G16,G17,G18,G19,G20,G21,G22)
A3: 2 | C3: 货币资金
A4: 3 | C4: 其中：受限货币资金
A5: 4 | C5: 结算备付金
A6: 5 | C6: 拆出资金
A7: 6 | C7: 交易性金融资产 / 短期投资
A8: 7 | C8: 衍生金融资产
A9: 8 | C9: 应收票据
A10: 9 | C10: 应收账款
A11: 10 | C11: 应收款项融资
A12: 11 | C12: 预付款项
A13: 12 | C13: 应收保费 / 应收分保账款
A14: 13 | C14: 应收利息
... A22: 21 | C22: 其他流动资产
A23: 22 | C23: 非流动资产合计 | D23: =SUM(D24,D25,D26,D27,D28,D29,D30,D31,D32,D34,D35,D36,D37,D38,D39,D40,D41,D42) | E23: =SUM(E24,E25,E26,E27,E28,E29,E30,E31,E32,E34,E35,E36,E37,E38,E39,E40,E41,E42) | F23: =SUM(F24,F25,F26,F27,F28,F29,F30,F31,F32,F34,F35,F36,F37,F38,F39,F40,F41,F42) | G23: =SUM(G24,G25,G26,G27,G28,G29,G30,G31,G32,G34,G35,G36,G37,G38,G39,G40,G41,G42)
A24: 23 | C24: 发放贷款和垫款
A25: 24 | C25: 债权投资 / 持有至到期投资
A26: 25 | C26: 其他债权投资 / 可供出售金融资产
A27: 26 | C27: 长期应收款
A28: 27 | C28: 长期股权投资
A29: 28 | C29: 其他权益工具投资
A30: 29 | C30: 其他非流动金融资产
A31: 30 | C31: 投资性房地产
A32: 31 | C32: 固定资产
A33: 32 | C33: 其中：固定资产清理
A34: 33 | C34: 在建工程
A35: 34 | C35: 生产性生物资产 / 油气资产
... A42: 41 | C42: 其他非流动资产
A43: 42 | C43: 资产总计 | D43: =D2+D23 | E43: =E2+E23 | F43: =F2+F23 | G43: =G2+G23
A44: 43 | C44: 流动负债合计 | D44: =SUM(D45,D46,D47,D48,D49,D50,D51,D52,D53,D54,D55,D56,D57,D60,D61,D62) | E44: =SUM(E45,E46,E47,E48,E49,E50,E51,E52,E53,E54,E55,E56,E57,E60,E61,E62) | F44: =SUM(F45,F46,F47,F48,F49,F50,F51,F52,F53,F54,F55,F56,F57,F60,F61,F62) | G44: =SUM(G45,G46,G47,G48,G49,G50,G51,G52,G53,G54,G55,G56,G57,G60,G61,G62)
A45: 44 | C45: 短期借款
A46: 45 | C46: 向中央银行借款
A47: 46 | C47: 拆入资金 / 吸收存款及同业存放
A48: 47 | C48: 交易性金融负债
A49: 48 | C49: 衍生金融负债
A50: 49 | C50: 应付票据
A51: 50 | C51: 应付账款
A52: 51 | C52: 预收款项
A53: 52 | C53: 合同负债
A54: 53 | C54: 卖出回购金融资产款
A55: 54 | C55: 应付职工薪酬
A56: 55 | C56: 应交税费
... A62: 61 | C62: 其他流动负债
A63: 62 | C63: 非流动负债合计 | D63: =SUM(D64,D65,D68,D69,D70,D71,D72,D73,D74) | E63: =SUM(E64,E65,E68,E69,E70,E71,E72,E73,E74) | F63: =SUM(F64,F65,F68,F69,F70,F71,F72,F73,F74) | G63: =SUM(G64,G65,G68,G69,G70,G71,G72,G73,G74)
A64: 63 | C64: 长期借款
A65: 64 | C65: 应付债券
A66: 65 | C66: 其中：优先股
A67: 66 | C67: 其中：永续债
A68: 67 | C68: 租赁负债
A69: 68 | C69: 长期应付款
A70: 69 | C70: 长期应付职工薪酬
A71: 70 | C71: 预计负债
A72: 71 | C72: 递延收益
A73: 72 | C73: 递延所得税负债
A74: 73 | C74: 其他非流动负债
A75: 74 | C75: 负债合计 | D75: =D44+D63 | E75: =E44+E63 | F75: =F44+F63 | G75: =G44+G63
A76: 75 | C76: 所有者权益合计 | D76: =D88+D89 | E76: =E88+E89 | F76: =F88+F89 | G76: =G88+G89
A77: 76 | C77: 实收资本 (或股本)
A78: 77 | C78: 其他权益工具
A79: 78 | C79: 其中：优先股 (权益类)
A80: 79 | C80: 其中：永续债 (权益类)
A81: 80 | C81: 资本公积
A82: 81 | C82: 减：库存股
A83: 82 | C83: 其他综合收益
A84: 83 | C84: 专项储备
A85: 84 | C85: 盈余公积
A86: 85 | C86: 一般风险准备
A87: 86 | C87: 未分配利润
A88: 87 | C88: 归属于母公司所有者权益合计 | D88: =SUM(D77,D78,D81,D83,D84,D85,D86,D87)-SUM(D82) | E88: =SUM(E77,E78,E81,E83,E84,E85,E86,E87)-SUM(E82) | F88: =SUM(F77,F78,F81,F83,F84,F85,F86,F87)-SUM(F82) | G88: =SUM(G77,G78,G81,G83,G84,G85,G86,G87)-SUM(G82)
A89: 88 | C89: 少数股东权益
A90: 89 | C90: 负债和所有者权益总计 | D90: =D75+D76 | E90: =E75+E76 | F90: =F75+F76 | G90: =G75+G76
A91: 90 | C91: 【配平检查】资产 - (负债+权益) | D91: =D43-D90 | E91: =E43-E90 | F91: =F43-F90 | G91: =G43-G90
A93: 91 | B93: 利润表 | C93: 营业总收入
A94: 92 | C94: 营业收入
A95: 93 | C95: 利息收入 / 手续费及佣金收入
A96: 94 | C96: 营业总成本
A97: 95 | C97: 营业成本
A98: 96 | C98: 利息支出 / 手续费及佣金支出
A99: 97 | C99: 税金及附加
A100: 98 | C100: 销售费用
A101: 99 | C101: 管理费用
A102: 100 | C102: 研发费用
A103: 101 | C103: 财务费用
A104: 102 | C104: 其中：利息费用
A105: 103 | C105: 其中：利息收入
... A114: 112 | C114: 资产处置收益
A115: 113 | C115: 营业利润 | D115: =D93-D96+D106+D107+D111-D112-D113+D114 | E115: =E93-E96+E106+E107+E111-E112-E113+E114 | F115: =F93-F96+F106+F107+F111-F112-F113+F114 | G115: =G93-G96+G106+G107+G111-G112-G113+G114
A116: 114 | C116: 加：营业外收入
A117: 115 | C117: 减：营业外支出
A118: 116 | C118: 利润总额 | D118: =D115+D116-D117 | E118: =E115+E116-E117 | F118: =F115+F116-F117 | G118: =G115+G116-G117
A119: 117 | C119: 减：所得税费用
A120: 118 | C120: 净利润 | D120: =D118-D119 | E120: =E118-E119 | F120: =F118-F119 | G120: =G118-G119
A121: 119 | C121: 归属于母公司所有者的净利润
A122: 120 | C122: 少数股东损益
A123: 121 | C123: 综合收益总额
A124: 122 | C124: 【利润勾稽】净利润 - (归母+少数) | D124: =D120-(D121+D122) | E124: =E120-(E121+E122) | F124: =F120-(F121+F122) | G124: =G120-(G121+G122)
A126: 123 | B126: 现金流量表 | C126: 经营活动产生的现金流量：
A127: 124 | C127: 销售商品、提供劳务收到的现金
A128: 125 | C128: 客户存款和同业存放款项净增加额
...

Sheet 5.担保人-本部源数据
A1: 序号 | B1: 报表分类 | C1: 标准会计科目 | D1: 2022年 | E1: 2023年 | F1: 2024年 | G1: 最新一期
A2: 1 | B2: 资产负债表 | C2: 流动资产合计 | D2: =SUM(D3,D5,D6,D7,D8,D9,D10,D11,D12,D13,D14,D15,D16,D17,D18,D19,D20,D21,D22) | E2: =SUM(E3,E5,E6,E7,E8,E9,E10,E11,E12,E13,E14,E15,E16,E17,E18,E19,E20,E21,E22) | F2: =SUM(F3,F5,F6,F7,F8,F9,F10,F11,F12,F13,F14,F15,F16,F17,F18,F19,F20,F21,F22) | G2: =SUM(G3,G5,G6,G7,G8,G9,G10,G11,G12,G13,G14,G15,G16,G17,G18,G19,G20,G21,G22)
A3: 2 | C3: 货币资金
A4: 3 | C4: 其中：受限货币资金
A5: 4 | C5: 结算备付金
A6: 5 | C6: 拆出资金
A7: 6 | C7: 交易性金融资产 / 短期投资
A8: 7 | C8: 衍生金融资产
A9: 8 | C9: 应收票据
A10: 9 | C10: 应收账款
A11: 10 | C11: 应收款项融资
A12: 11 | C12: 预付款项
A13: 12 | C13: 应收保费 / 应收分保账款
A14: 13 | C14: 应收利息
... A22: 21 | C22: 其他流动资产
A23: 22 | C23: 非流动资产合计 | D23: =SUM(D24,D25,D26,D27,D28,D29,D30,D31,D32,D34,D35,D36,D37,D38,D39,D40,D41,D42) | E23: =SUM(E24,E25,E26,E27,E28,E29,E30,E31,E32,E34,E35,E36,E37,E38,E39,E40,E41,E42) | F23: =SUM(F24,F25,F26,F27,F28,F29,F30,F31,F32,F34,F35,F36,F37,F38,F39,F40,F41,F42) | G23: =SUM(G24,G25,G26,G27,G28,G29,G30,G31,G32,G34,G35,G36,G37,G38,G39,G40,G41,G42)
A24: 23 | C24: 发放贷款和垫款
A25: 24 | C25: 债权投资 / 持有至到期投资
A26: 25 | C26: 其他债权投资 / 可供出售金融资产
A27: 26 | C27: 长期应收款
A28: 27 | C28: 长期股权投资
A29: 28 | C29: 其他权益工具投资
A30: 29 | C30: 其他非流动金融资产
A31: 30 | C31: 投资性房地产
A32: 31 | C32: 固定资产
A33: 32 | C33: 其中：固定资产清理
A34: 33 | C34: 在建工程
A35: 34 | C35: 生产性生物资产 / 油气资产
... A42: 41 | C42: 其他非流动资产
A43: 42 | C43: 资产总计 | D43: =D2+D23 | E43: =E2+E23 | F43: =F2+F23 | G43: =G2+G23
A44: 43 | C44: 流动负债合计 | D44: =SUM(D45,D46,D47,D48,D49,D50,D51,D52,D53,D54,D55,D56,D57,D60,D61,D62) | E44: =SUM(E45,E46,E47,E48,E49,E50,E51,E52,E53,E54,E55,E56,E57,E60,E61,E62) | F44: =SUM(F45,F46,F47,F48,F49,F50,F51,F52,F53,F54,F55,F56,F57,F60,F61,F62) | G44: =SUM(G45,G46,G47,G48,G49,G50,G51,G52,G53,G54,G55,G56,G57,G60,G61,G62)
A45: 44 | C45: 短期借款
A46: 45 | C46: 向中央银行借款
A47: 46 | C47: 拆入资金 / 吸收存款及同业存放
A48: 47 | C48: 交易性金融负债
A49: 48 | C49: 衍生金融负债
A50: 49 | C50: 应付票据
A51: 50 | C51: 应付账款
A52: 51 | C52: 预收款项
A53: 52 | C53: 合同负债
A54: 53 | C54: 卖出回购金融资产款
A55: 54 | C55: 应付职工薪酬
A56: 55 | C56: 应交税费
... A62: 61 | C62: 其他流动负债
A63: 62 | C63: 非流动负债合计 | D63: =SUM(D64,D65,D68,D69,D70,D71,D72,D73,D74) | E63: =SUM(E64,E65,E68,E69,E70,E71,E72,E73,E74) | F63: =SUM(F64,F65,F68,F69,F70,F71,F72,F73,F74) | G63: =SUM(G64,G65,G68,G69,G70,G71,G72,G73,G74)
A64: 63 | C64: 长期借款
A65: 64 | C65: 应付债券
A66: 65 | C66: 其中：优先股
A67: 66 | C67: 其中：永续债
A68: 67 | C68: 租赁负债
A69: 68 | C69: 长期应付款
A70: 69 | C70: 长期应付职工薪酬
A71: 70 | C71: 预计负债
A72: 71 | C72: 递延收益
A73: 72 | C73: 递延所得税负债
A74: 73 | C74: 其他非流动负债
A75: 74 | C75: 负债合计 | D75: =D44+D63 | E75: =E44+E63 | F75: =F44+F63 | G75: =G44+G63
A76: 75 | C76: 所有者权益合计 | D76: =D88+D89 | E76: =E88+E89 | F76: =F88+F89 | G76: =G88+G89
A77: 76 | C77: 实收资本 (或股本)
A78: 77 | C78: 其他权益工具
A79: 78 | C79: 其中：优先股 (权益类)
A80: 79 | C80: 其中：永续债 (权益类)
A81: 80 | C81: 资本公积
A82: 81 | C82: 减：库存股
A83: 82 | C83: 其他综合收益
A84: 83 | C84: 专项储备
A85: 84 | C85: 盈余公积
A86: 85 | C86: 一般风险准备
A87: 86 | C87: 未分配利润
A88: 87 | C88: 归属于母公司所有者权益合计 | D88: =SUM(D77,D78,D81,D83,D84,D85,D86,D87)-SUM(D82) | E88: =SUM(E77,E78,E81,E83,E84,E85,E86,E87)-SUM(E82) | F88: =SUM(F77,F78,F81,F83,F84,F85,F86,F87)-SUM(F82) | G88: =SUM(G77,G78,G81,G83,G84,G85,G86,G87)-SUM(G82)
A89: 88 | C89: 少数股东权益
A90: 89 | C90: 负债和所有者权益总计 | D90: =D75+D76 | E90: =E75+E76 | F90: =F75+F76 | G90: =G75+G76
A91: 90 | C91: 【配平检查】资产 - (负债+权益) | D91: =D43-D90 | E91: =E43-E90 | F91: =F43-F90 | G91: =G43-G90
A93: 91 | B93: 利润表 | C93: 营业总收入
A94: 92 | C94: 营业收入
A95: 93 | C95: 利息收入 / 手续费及佣金收入
A96: 94 | C96: 营业总成本
A97: 95 | C97: 营业成本
A98: 96 | C98: 利息支出 / 手续费及佣金支出
A99: 97 | C99: 税金及附加
A100: 98 | C100: 销售费用
A101: 99 | C101: 管理费用
A102: 100 | C102: 研发费用
A103: 101 | C103: 财务费用
A104: 102 | C104: 其中：利息费用
A105: 103 | C105: 其中：利息收入
... A114: 112 | C114: 资产处置收益
A115: 113 | C115: 营业利润 | D115: =D93-D96+D106+D107+D111-D112-D113+D114 | E115: =E93-E96+E106+E107+E111-E112-E113+E114 | F115: =F93-F96+F106+F107+F111-F112-F113+F114 | G115: =G93-G96+G106+G107+G111-G112-G113+G114
A116: 114 | C116: 加：营业外收入
A117: 115 | C117: 减：营业外支出
A118: 116 | C118: 利润总额 | D118: =D115+D116-D117 | E118: =E115+E116-E117 | F118: =F115+F116-F117 | G118: =G115+G116-G117
A119: 117 | C119: 减：所得税费用
A120: 118 | C120: 净利润 | D120: =D118-D119 | E120: =E118-E119 | F120: =F118-F119 | G120: =G118-G119
A121: 119 | C121: 归属于母公司所有者的净利润
A122: 120 | C122: 少数股东损益
A123: 121 | C123: 综合收益总额
A124: 122 | C124: 【利润勾稽】净利润 - (归母+少数) | D124: =D120-(D121+D122) | E124: =E120-(E121+E122) | F124: =F120-(F121+F122) | G124: =G120-(G121+G122)
A126: 123 | B126: 现金流量表 | C126: 经营活动产生的现金流量：
A127: 124 | C127: 销售商品、提供劳务收到的现金
A128: 125 | C128: 客户存款和同业存放款项净增加额
...

Sheet 6.担保人-财务分析
A1: 分析板块 | B1: 财务分析科目 | C1: 合并口径 (单位:万元) | G1: 本部口径 (单位:万元)
C2: 2022年 | D2: 2023年 | E2: 2024年 | F2: 最新一期 | G2: 2022年 | H2: 2023年 | I2: 2024年 | J2: 最新一期
A3: 资产 | B3: 总资产 | C3: ='4.担保人-合并源数据'!D43/10000 | D3: ='4.担保人-合并源数据'!E43/10000 | E3: ='4.担保人-合并源数据'!F43/10000 | F3: ='4.担保人-合并源数据'!G43/10000 | G3: ='5.担保人-本部源数据'!D43/10000 | H3: ='5.担保人-本部源数据'!E43/10000 | I3: ='5.担保人-本部源数据'!F43/10000 | J3: ='5.担保人-本部源数据'!G43/10000
B4: 流动资产 | C4: ='4.担保人-合并源数据'!D2/10000 | D4: ='4.担保人-合并源数据'!E2/10000 | E4: ='4.担保人-合并源数据'!F2/10000 | F4: ='4.担保人-合并源数据'!G2/10000 | G4: ='5.担保人-本部源数据'!D2/10000 | H4: ='5.担保人-本部源数据'!E2/10000 | I4: ='5.担保人-本部源数据'!F2/10000 | J4: ='5.担保人-本部源数据'!G2/10000
B5: 货币资金 | C5: ='4.担保人-合并源数据'!D3/10000 | D5: ='4.担保人-合并源数据'!E3/10000 | E5: ='4.担保人-合并源数据'!F3/10000 | F5: ='4.担保人-合并源数据'!G3/10000 | G5: ='5.担保人-本部源数据'!D3/10000 | H5: ='5.担保人-本部源数据'!E3/10000 | I5: ='5.担保人-本部源数据'!F3/10000 | J5: ='5.担保人-本部源数据'!G3/10000
B6: 应收帐款 | C6: ='4.担保人-合并源数据'!D10/10000 | D6: ='4.担保人-合并源数据'!E10/10000 | E6: ='4.担保人-合并源数据'!F10/10000 | F6: ='4.担保人-合并源数据'!G10/10000 | G6: ='5.担保人-本部源数据'!D10/10000 | H6: ='5.担保人-本部源数据'!E10/10000 | I6: ='5.担保人-本部源数据'!F10/10000 | J6: ='5.担保人-本部源数据'!G10/10000
B7: 其他应收款 | C7: ='4.担保人-合并源数据'!D16/10000 | D7: ='4.担保人-合并源数据'!E16/10000 | E7: ='4.担保人-合并源数据'!F16/10000 | F7: ='4.担保人-合并源数据'!G16/10000 | G7: ='5.担保人-本部源数据'!D16/10000 | H7: ='5.担保人-本部源数据'!E16/10000 | I7: ='5.担保人-本部源数据'!F16/10000 | J7: ='5.担保人-本部源数据'!G16/10000
B8: 预付帐款 | C8: ='4.担保人-合并源数据'!D12/10000 | D8: ='4.担保人-合并源数据'!E12/10000 | E8: ='4.担保人-合并源数据'!F12/10000 | F8: ='4.担保人-合并源数据'!G12/10000 | G8: ='5.担保人-本部源数据'!D12/10000 | H8: ='5.担保人-本部源数据'!E12/10000 | I8: ='5.担保人-本部源数据'!F12/10000 | J8: ='5.担保人-本部源数据'!G12/10000
B9: 存货 | C9: ='4.担保人-合并源数据'!D18/10000 | D9: ='4.担保人-合并源数据'!E18/10000 | E9: ='4.担保人-合并源数据'!F18/10000 | F9: ='4.担保人-合并源数据'!G18/10000 | G9: ='5.担保人-本部源数据'!D18/10000 | H9: ='5.担保人-本部源数据'!E18/10000 | I9: ='5.担保人-本部源数据'!F18/10000 | J9: ='5.担保人-本部源数据'!G18/10000
B10: 其他流动资产 | C10: ='4.担保人-合并源数据'!D22/10000 | D10: ='4.担保人-合并源数据'!E22/10000 | E10: ='4.担保人-合并源数据'!F22/10000 | F10: ='4.担保人-合并源数据'!G22/10000 | G10: ='5.担保人-本部源数据'!D22/10000 | H10: ='5.担保人-本部源数据'!E22/10000 | I10: ='5.担保人-本部源数据'!F22/10000 | J10: ='5.担保人-本部源数据'!G22/10000
B11: 持有至到期投资 | C11: ='4.担保人-合并源数据'!D25/10000 | D11: ='4.担保人-合并源数据'!E25/10000 | E11: ='4.担保人-合并源数据'!F25/10000 | F11: ='4.担保人-合并源数据'!G25/10000 | G11: ='5.担保人-本部源数据'!D25/10000 | H11: ='5.担保人-本部源数据'!E25/10000 | I11: ='5.担保人-本部源数据'!F25/10000 | J11: ='5.担保人-本部源数据'!G25/10000
B12: 长期股权投资 | C12: ='4.担保人-合并源数据'!D28/10000 | D12: ='4.担保人-合并源数据'!E28/10000 | E12: ='4.担保人-合并源数据'!F28/10000 | F12: ='4.担保人-合并源数据'!G28/10000 | G12: ='5.担保人-本部源数据'!D28/10000 | H12: ='5.担保人-本部源数据'!E28/10000 | I12: ='5.担保人-本部源数据'!F28/10000 | J12: ='5.担保人-本部源数据'!G28/10000
B13: 投资性房地产 | C13: ='4.担保人-合并源数据'!D31/10000 | D13: ='4.担保人-合并源数据'!E31/10000 | E13: ='4.担保人-合并源数据'!F31/10000 | F13: ='4.担保人-合并源数据'!G31/10000 | G13: ='5.担保人-本部源数据'!D31/10000 | H13: ='5.担保人-本部源数据'!E31/10000 | I13: ='5.担保人-本部源数据'!F31/10000 | J13: ='5.担保人-本部源数据'!G31/10000
B14: 固定资产 | C14: ='4.担保人-合并源数据'!D32/10000 | D14: ='4.担保人-合并源数据'!E32/10000 | E14: ='4.担保人-合并源数据'!F32/10000 | F14: ='4.担保人-合并源数据'!G32/10000 | G14: ='5.担保人-本部源数据'!D32/10000 | H14: ='5.担保人-本部源数据'!E32/10000 | I14: ='5.担保人-本部源数据'!F32/10000 | J14: ='5.担保人-本部源数据'!G32/10000
B15: 其中：本期新增折旧
B16: 在建工程 | C16: ='4.担保人-合并源数据'!D34/10000 | D16: ='4.担保人-合并源数据'!E34/10000 | E16: ='4.担保人-合并源数据'!F34/10000 | F16: ='4.担保人-合并源数据'!G34/10000 | G16: ='5.担保人-本部源数据'!D34/10000 | H16: ='5.担保人-本部源数据'!E34/10000 | I16: ='5.担保人-本部源数据'!F34/10000 | J16: ='5.担保人-本部源数据'!G34/10000
B17: 无形资产 | C17: ='4.担保人-合并源数据'!D37/10000 | D17: ='4.担保人-合并源数据'!E37/10000 | E17: ='4.担保人-合并源数据'!F37/10000 | F17: ='4.担保人-合并源数据'!G37/10000 | G17: ='5.担保人-本部源数据'!D37/10000 | H17: ='5.担保人-本部源数据'!E37/10000 | I17: ='5.担保人-本部源数据'!F37/10000 | J17: ='5.担保人-本部源数据'!G37/10000
B18: 其中：本期新增摊销
B19: 长期待摊费用 | C19: ='4.担保人-合并源数据'!D40/10000 | D19: ='4.担保人-合并源数据'!E40/10000 | E19: ='4.担保人-合并源数据'!F40/10000 | F19: ='4.担保人-合并源数据'!G40/10000 | G19: ='5.担保人-本部源数据'!D40/10000 | H19: ='5.担保人-本部源数据'!E40/10000 | I19: ='5.担保人-本部源数据'!F40/10000 | J19: ='5.担保人-本部源数据'!G40/10000
B20: 其中：本期新增摊销(长待)
B21: 递延所得税资产 | C21: ='4.担保人-合并源数据'!D41/10000 | D21: ='4.担保人-合并源数据'!E41/10000 | E21: ='4.担保人-合并源数据'!F41/10000 | F21: ='4.担保人-合并源数据'!G41/10000 | G21: ='5.担保人-本部源数据'!D41/10000 | H21: ='5.担保人-本部源数据'!E41/10000 | I21: ='5.担保人-本部源数据'!F41/10000 | J21: ='5.担保人-本部源数据'!G41/10000
B22: 其他非流动资产 | C22: ='4.担保人-合并源数据'!D42/10000 | D22: ='4.担保人-合并源数据'!E42/10000 | E22: ='4.担保人-合并源数据'!F42/10000 | F22: ='4.担保人-合并源数据'!G42/10000 | G22: ='5.担保人-本部源数据'!D42/10000 | H22: ='5.担保人-本部源数据'!E42/10000 | I22: ='5.担保人-本部源数据'!F42/10000 | J22: ='5.担保人-本部源数据'!G42/10000
A23: 负债 | B23: 总负债 | C23: ='4.担保人-合并源数据'!D75/10000 | D23: ='4.担保人-合并源数据'!E75/10000 | E23: ='4.担保人-合并源数据'!F75/10000 | F23: ='4.担保人-合并源数据'!G75/10000 | G23: ='5.担保人-本部源数据'!D75/10000 | H23: ='5.担保人-本部源数据'!E75/10000 | I23: ='5.担保人-本部源数据'!F75/10000 | J23: ='5.担保人-本部源数据'!G75/10000
B24: 流动负债 | C24: ='4.担保人-合并源数据'!D44/10000 | D24: ='4.担保人-合并源数据'!E44/10000 | E24: ='4.担保人-合并源数据'!F44/10000 | F24: ='4.担保人-合并源数据'!G44/10000 | G24: ='5.担保人-本部源数据'!D44/10000 | H24: ='5.担保人-本部源数据'!E44/10000 | I24: ='5.担保人-本部源数据'!F44/10000 | J24: ='5.担保人-本部源数据'!G44/10000
B25: 短期借款 | C25: ='4.担保人-合并源数据'!D45/10000 | D25: ='4.担保人-合并源数据'!E45/10000 | E25: ='4.担保人-合并源数据'!F45/10000 | F25: ='4.担保人-合并源数据'!G45/10000 | G25: ='5.担保人-本部源数据'!D45/10000 | H25: ='5.担保人-本部源数据'!E45/10000 | I25: ='5.担保人-本部源数据'!F45/10000 | J25: ='5.担保人-本部源数据'!G45/10000
B26: 应付账款 | C26: ='4.担保人-合并源数据'!D51/10000 | D26: ='4.担保人-合并源数据'!E51/10000 | E26: ='4.担保人-合并源数据'!F51/10000 | F26: ='4.担保人-合并源数据'!G51/10000 | G26: ='5.担保人-本部源数据'!D51/10000 | H26: ='5.担保人-本部源数据'!E51/10000 | I26: ='5.担保人-本部源数据'!F51/10000 | J26: ='5.担保人-本部源数据'!G51/10000
B27: 预收账款 | C27: ='4.担保人-合并源数据'!D52/10000 | D27: ='4.担保人-合并源数据'!E52/10000 | E27: ='4.担保人-合并源数据'!F52/10000 | F27: ='4.担保人-合并源数据'!G52/10000 | G27: ='5.担保人-本部源数据'!D52/10000 | H27: ='5.担保人-本部源数据'!E52/10000 | I27: ='5.担保人-本部源数据'!F52/10000 | J27: ='5.担保人-本部源数据'!G52/10000
B28: 应付职工薪酬 | C28: ='4.担保人-合并源数据'!D55/10000 | D28: ='4.担保人-合并源数据'!E55/10000 | E28: ='4.担保人-合并源数据'!F55/10000 | F28: ='4.担保人-合并源数据'!G55/10000 | G28: ='5.担保人-本部源数据'!D55/10000 | H28: ='5.担保人-本部源数据'!E55/10000 | I28: ='5.担保人-本部源数据'!F55/10000 | J28: ='5.担保人-本部源数据'!G55/10000
B29: 应交税费 | C29: ='4.担保人-合并源数据'!D56/10000 | D29: ='4.担保人-合并源数据'!E56/10000 | E29: ='4.担保人-合并源数据'!F56/10000 | F29: ='4.担保人-合并源数据'!G56/10000 | G29: ='5.担保人-本部源数据'!D56/10000 | H29: ='5.担保人-本部源数据'!E56/10000 | I29: ='5.担保人-本部源数据'!F56/10000 | J29: ='5.担保人-本部源数据'!G56/10000
B30: 其他应付款 | C30: ='4.担保人-合并源数据'!D57/10000 | D30: ='4.担保人-合并源数据'!E57/10000 | E30: ='4.担保人-合并源数据'!F57/10000 | F30: ='4.担保人-合并源数据'!G57/10000 | G30: ='5.担保人-本部源数据'!D57/10000 | H30: ='5.担保人-本部源数据'!E57/10000 | I30: ='5.担保人-本部源数据'!F57/10000 | J30: ='5.担保人-本部源数据'!G57/10000
B31: 一年内的到期的非流动负债 | C31: ='4.担保人-合并源数据'!D61/10000 | D31: ='4.担保人-合并源数据'!E61/10000 | E31: ='4.担保人-合并源数据'!F61/10000 | F31: ='4.担保人-合并源数据'!G61/10000 | G31: ='5.担保人-本部源数据'!D61/10000 | H31: ='5.担保人-本部源数据'!E61/10000 | I31: ='5.担保人-本部源数据'!F61/10000 | J31: ='5.担保人-本部源数据'!G61/10000
B32: 长期借款 | C32: ='4.担保人-合并源数据'!D64/10000 | D32: ='4.担保人-合并源数据'!E64/10000 | E32: ='4.担保人-合并源数据'!F64/10000 | F32: ='4.担保人-合并源数据'!G64/10000 | G32: ='5.担保人-本部源数据'!D64/10000 | H32: ='5.担保人-本部源数据'!E64/10000 | I32: ='5.担保人-本部源数据'!F64/10000 | J32: ='5.担保人-本部源数据'!G64/10000
B33: 长期应付款 | C33: ='4.担保人-合并源数据'!D69/10000 | D33: ='4.担保人-合并源数据'!E69/10000 | E33: ='4.担保人-合并源数据'!F69/10000 | F33: ='4.担保人-合并源数据'!G69/10000 | G33: ='5.担保人-本部源数据'!D69/10000 | H33: ='5.担保人-本部源数据'!E69/10000 | I33: ='5.担保人-本部源数据'!F69/10000 | J33: ='5.担保人-本部源数据'!G69/10000
B34: 应付债券 | C34: ='4.担保人-合并源数据'!D65/10000 | D34: ='4.担保人-合并源数据'!E65/10000 | E34: ='4.担保人-合并源数据'!F65/10000 | F34: ='4.担保人-合并源数据'!G65/10000 | G34: ='5.担保人-本部源数据'!D65/10000 | H34: ='5.担保人-本部源数据'!E65/10000 | I34: ='5.担保人-本部源数据'!F65/10000 | J34: ='5.担保人-本部源数据'!G65/10000
A35: 权益 | B35: 净资产 | C35: ='4.担保人-合并源数据'!D76/10000 | D35: ='4.担保人-合并源数据'!E76/10000 | E35: ='4.担保人-合并源数据'!F76/10000 | F35: ='4.担保人-合并源数据'!G76/10000 | G35: ='5.担保人-本部源数据'!D76/10000 | H35: ='5.担保人-本部源数据'!E76/10000 | I35: ='5.担保人-本部源数据'!F76/10000 | J35: ='5.担保人-本部源数据'!G76/10000
B36: 实收资本 | C36: ='4.担保人-合并源数据'!D77/10000 | D36: ='4.担保人-合并源数据'!E77/10000 | E36: ='4.担保人-合并源数据'!F77/10000 | F36: ='4.担保人-合并源数据'!G77/10000 | G36: ='5.担保人-本部源数据'!D77/10000 | H36: ='5.担保人-本部源数据'!E77/10000 | I36: ='5.担保人-本部源数据'!F77/10000 | J36: ='5.担保人-本部源数据'!G77/10000
B37: 资本公积 | C37: ='4.担保人-合并源数据'!D81/10000 | D37: ='4.担保人-合并源数据'!E81/10000 | E37: ='4.担保人-合并源数据'!F81/10000 | F37: ='4.担保人-合并源数据'!G81/10000 | G37: ='5.担保人-本部源数据'!D81/10000 | H37: ='5.担保人-本部源数据'!E81/10000 | I37: ='5.担保人-本部源数据'!F81/10000 | J37: ='5.担保人-本部源数据'!G81/10000
B38: 盈余公积 | C38: ='4.担保人-合并源数据'!D85/10000 | D38: ='4.担保人-合并源数据'!E85/10000 | E38: ='4.担保人-合并源数据'!F85/10000 | F38: ='4.担保人-合并源数据'!G85/10000 | G38: ='5.担保人-本部源数据'!D85/10000 | H38: ='5.担保人-本部源数据'!E85/10000 | I38: ='5.担保人-本部源数据'!F85/10000 | J38: ='5.担保人-本部源数据'!G85/10000
B39: 未分配利润 | C39: ='4.担保人-合并源数据'!D87/10000 | D39: ='4.担保人-合并源数据'!E87/10000 | E39: ='4.担保人-合并源数据'!F87/10000 | F39: ='4.担保人-合并源数据'!G87/10000 | G39: ='5.担保人-本部源数据'!D87/10000 | H39: ='5.担保人-本部源数据'!E87/10000 | I39: ='5.担保人-本部源数据'!F87/10000 | J39: ='5.担保人-本部源数据'!G87/10000
A40: 盈利能力 | B40: 营业收入 | C40: ='4.担保人-合并源数据'!D94/10000 | D40: ='4.担保人-合并源数据'!E94/10000 | E40: ='4.担保人-合并源数据'!F94/10000 | F40: ='4.担保人-合并源数据'!G94/10000 | G40: ='5.担保人-本部源数据'!D94/10000 | H40: ='5.担保人-本部源数据'!E94/10000 | I40: ='5.担保人-本部源数据'!F94/10000 | J40: ='5.担保人-本部源数据'!G94/10000
B41: 主营业务成本 | C41: ='4.担保人-合并源数据'!D97/10000 | D41: ='4.担保人-合并源数据'!E97/10000 | E41: ='4.担保人-合并源数据'!F97/10000 | F41: ='4.担保人-合并源数据'!G97/10000 | G41: ='5.担保人-本部源数据'!D97/10000 | H41: ='5.担保人-本部源数据'!E97/10000 | I41: ='5.担保人-本部源数据'!F97/10000 | J41: ='5.担保人-本部源数据'!G97/10000
B42: 主营业务利润 | C42: =('4.担保人-合并源数据'!D94 - '4.担保人-合并源数据'!D97)/10000 | D42: =('4.担保人-合并源数据'!E94 - '4.担保人-合并源数据'!E97)/10000 | E42: =('4.担保人-合并源数据'!F94 - '4.担保人-合并源数据'!F97)/10000 | F42: =('4.担保人-合并源数据'!G94 - '4.担保人-合并源数据'!G97)/10000 | G42: =('5.担保人-本部源数据'!D94 - '5.担保人-本部源数据'!D97)/10000 | H42: =('5.担保人-本部源数据'!E94 - '5.担保人-本部源数据'!E97)/10000 | I42: =('5.担保人-本部源数据'!F94 - '5.担保人-本部源数据'!F97)/10000 | J42: =('5.担保人-本部源数据'!G94 - '5.担保人-本部源数据'!G97)/10000
B43: 期间费用 | C43: =('4.担保人-合并源数据'!D100 + '4.担保人-合并源数据'!D101 + '4.担保人-合并源数据'!D102 + '4.担保人-合并源数据'!D103)/10000 | D43: =('4.担保人-合并源数据'!E100 + '4.担保人-合并源数据'!E101 + '4.担保人-合并源数据'!E102 + '4.担保人-合并源数据'!E103)/10000 | E43: =('4.担保人-合并源数据'!F100 + '4.担保人-合并源数据'!F101 + '4.担保人-合并源数据'!F102 + '4.担保人-合并源数据'!F103)/10000 | F43: =('4.担保人-合并源数据'!G100 + '4.担保人-合并源数据'!G101 + '4.担保人-合并源数据'!G102 + '4.担保人-合并源数据'!G103)/10000 | G43: =('5.担保人-本部源数据'!D100 + '5.担保人-本部源数据'!D101 + '5.担保人-本部源数据'!D102 + '5.担保人-本部源数据'!D103)/10000 | H43: =('5.担保人-本部源数据'!E100 + '5.担保人-本部源数据'!E101 + '5.担保人-本部源数据'!E102 + '5.担保人-本部源数据'!E103)/10000 | I43: =('5.担保人-本部源数据'!F100 + '5.担保人-本部源数据'!F101 + '5.担保人-本部源数据'!F102 + '5.担保人-本部源数据'!F103)/10000 | J43: =('5.担保人-本部源数据'!G100 + '5.担保人-本部源数据'!G101 + '5.担保人-本部源数据'!G102 + '5.担保人-本部源数据'!G103)/10000
B44: 股权变动收益 | C44: ='4.担保人-合并源数据'!D107/10000 | D44: ='4.担保人-合并源数据'!E107/10000 | E44: ='4.担保人-合并源数据'!F107/10000 | F44: ='4.担保人-合并源数据'!G107/10000 | G44: ='5.担保人-本部源数据'!D107/10000 | H44: ='5.担保人-本部源数据'!E107/10000 | I44: ='5.担保人-本部源数据'!F107/10000 | J44: ='5.担保人-本部源数据'!G107/10000
B45: 其他收益（政府补助） | C45: ='4.担保人-合并源数据'!D106/10000 | D45: ='4.担保人-合并源数据'!E106/10000 | E45: ='4.担保人-合并源数据'!F106/10000 | F45: ='4.担保人-合并源数据'!G106/10000 | G45: ='5.担保人-本部源数据'!D106/10000 | H45: ='5.担保人-本部源数据'!E106/10000 | I45: ='5.担保人-本部源数据'!F106/10000 | J45: ='5.担保人-本部源数据'!G106/10000
B46: 利润总额 | C46: ='4.担保人-合并源数据'!D118/10000 | D46: ='4.担保人-合并源数据'!E118/10000 | E46: ='4.担保人-合并源数据'!F118/10000 | F46: ='4.担保人-合并源数据'!G118/10000 | G46: ='5.担保人-本部源数据'!D118/10000 | H46: ='5.担保人-本部源数据'!E118/10000 | I46: ='5.担保人-本部源数据'!F118/10000 | J46: ='5.担保人-本部源数据'!G118/10000
B47: 净利润 | C47: ='4.担保人-合并源数据'!D120/10000 | D47: ='4.担保人-合并源数据'!E120/10000 | E47: ='4.担保人-合并源数据'!F120/10000 | F47: ='4.担保人-合并源数据'!G120/10000 | G47: ='5.担保人-本部源数据'!D120/10000 | H47: ='5.担保人-本部源数据'!E120/10000 | I47: ='5.担保人-本部源数据'!F120/10000 | J47: ='5.担保人-本部源数据'!G120/10000
B48: 主营业务利润率 | C48: =IF('4.担保人-合并源数据'!D94=0, 0, ('4.担保人-合并源数据'!D94 - '4.担保人-合并源数据'!D97) / '4.担保人-合并源数据'!D94) | D48: =IF('4.担保人-合并源数据'!E94=0, 0, ('4.担保人-合并源数据'!E94 - '4.担保人-合并源数据'!E97) / '4.担保人-合并源数据'!E94) | E48: =IF('4.担保人-合并源数据'!F94=0, 0, ('4.担保人-合并源数据'!F94 - '4.担保人-合并源数据'!F97) / '4.担保人-合并源数据'!F94) | F48: =IF('4.担保人-合并源数据'!G94=0, 0, ('4.担保人-合并源数据'!G94 - '4.担保人-合并源数据'!G97) / '4.担保人-合并源数据'!G94) | G48: =IF('5.担保人-本部源数据'!D94=0, 0, ('5.担保人-本部源数据'!D94 - '5.担保人-本部源数据'!D97) / '5.担保人-本部源数据'!D94) | H48: =IF('5.担保人-本部源数据'!E94=0, 0, ('5.担保人-本部源数据'!E94 - '5.担保人-本部源数据'!E97) / '5.担保人-本部源数据'!E94) | I48: =IF('5.担保人-本部源数据'!F94=0, 0, ('5.担保人-本部源数据'!F94 - '5.担保人-本部源数据'!F97) / '5.担保人-本部源数据'!F94) | J48: =IF('5.担保人-本部源数据'!G94=0, 0, ('5.担保人-本部源数据'!G94 - '5.担保人-本部源数据'!G97) / '5.担保人-本部源数据'!G94)
B49: 期间费用率 | C49: =IF('4.担保人-合并源数据'!D94=0, 0, ('4.担保人-合并源数据'!D100 + '4.担保人-合并源数据'!D101 + '4.担保人-合并源数据'!D102 + '4.担保人-合并源数据'!D103) / '4.担保人-合并源数据'!D94) | D49: =IF('4.担保人-合并源数据'!E94=0, 0, ('4.担保人-合并源数据'!E100 + '4.担保人-合并源数据'!E101 + '4.担保人-合并源数据'!E102 + '4.担保人-合并源数据'!E103) / '4.担保人-合并源数据'!E94) | E49: =IF('4.担保人-合并源数据'!F94=0, 0, ('4.担保人-合并源数据'!F100 + '4.担保人-合并源数据'!F101 + '4.担保人-合并源数据'!F102 + '4.担保人-合并源数据'!F103) / '4.担保人-合并源数据'!F94) | F49: =IF('4.担保人-合并源数据'!G94=0, 0, ('4.担保人-合并源数据'!G100 + '4.担保人-合并源数据'!G101 + '4.担保人-合并源数据'!G102 + '4.担保人-合并源数据'!G103) / '4.担保人-合并源数据'!G94) | G49: =IF('5.担保人-本部源数据'!D94=0, 0, ('5.担保人-本部源数据'!D100 + '5.担保人-本部源数据'!D101 + '5.担保人-本部源数据'!D102 + '5.担保人-本部源数据'!D103) / '5.担保人-本部源数据'!D94) | H49: =IF('5.担保人-本部源数据'!E94=0, 0, ('5.担保人-本部源数据'!E100 + '5.担保人-本部源数据'!E101 + '5.担保人-本部源数据'!E102 + '5.担保人-本部源数据'!E103) / '5.担保人-本部源数据'!E94) | I49: =IF('5.担保人-本部源数据'!F94=0, 0, ('5.担保人-本部源数据'!F100 + '5.担保人-本部源数据'!F101 + '5.担保人-本部源数据'!F102 + '5.担保人-本部源数据'!F103) / '5.担保人-本部源数据'!F94) | J49: =IF('5.担保人-本部源数据'!G94=0, 0, ('5.担保人-本部源数据'!G100 + '5.担保人-本部源数据'!G101 + '5.担保人-本部源数据'!G102 + '5.担保人-本部源数据'!G103) / '5.担保人-本部源数据'!G94)
B50: 净利率 | C50: =IF('4.担保人-合并源数据'!D94=0, 0, '4.担保人-合并源数据'!D120 / '4.担保人-合并源数据'!D94) | D50: =IF('4.担保人-合并源数据'!E94=0, 0, '4.担保人-合并源数据'!E120 / '4.担保人-合并源数据'!E94) | E50: =IF('4.担保人-合并源数据'!F94=0, 0, '4.担保人-合并源数据'!F120 / '4.担保人-合并源数据'!F94) | F50: =IF('4.担保人-合并源数据'!G94=0, 0, '4.担保人-合并源数据'!G120 / '4.担保人-合并源数据'!G94) | G50: =IF('5.担保人-本部源数据'!D94=0, 0, '5.担保人-本部源数据'!D120 / '5.担保人-本部源数据'!D94) | H50: =IF('5.担保人-本部源数据'!E94=0, 0, '5.担保人-本部源数据'!E120 / '5.担保人-本部源数据'!E94) | I50: =IF('5.担保人-本部源数据'!F94=0, 0, '5.担保人-本部源数据'!F120 / '5.担保人-本部源数据'!F94) | J50: =IF('5.担保人-本部源数据'!G94=0, 0, '5.担保人-本部源数据'!G120 / '5.担保人-本部源数据'!G94)
A51: 营运能力 | B51: 应收账款周转天数 | C51: =IF('4.担保人-合并源数据'!D94=0, 0, 360 * '4.担保人-合并源数据'!D10 / '4.担保人-合并源数据'!D94) | D51: =IF('4.担保人-合并源数据'!E94=0, 0, 360 * '4.担保人-合并源数据'!E10 / '4.担保人-合并源数据'!E94) | E51: =IF('4.担保人-合并源数据'!F94=0, 0, 360 * '4.担保人-合并源数据'!F10 / '4.担保人-合并源数据'!F94) | F51: =IF('4.担保人-合并源数据'!G94=0, 0, 360 * '4.担保人-合并源数据'!G10 / '4.担保人-合并源数据'!G94) | G51: =IF('5.担保人-本部源数据'!D94=0, 0, 360 * '5.担保人-本部源数据'!D10 / '5.担保人-本部源数据'!D94) | H51: =IF('5.担保人-本部源数据'!E94=0, 0, 360 * '5.担保人-本部源数据'!E10 / '5.担保人-本部源数据'!E94) | I51: =IF('5.担保人-本部源数据'!F94=0, 0, 360 * '5.担保人-本部源数据'!F10 / '5.担保人-本部源数据'!F94) | J51: =IF('5.担保人-本部源数据'!G94=0, 0, 360 * '5.担保人-本部源数据'!G10 / '5.担保人-本部源数据'!G94)
B52: 存货周转天数 | C52: =IF('4.担保人-合并源数据'!D97=0, 0, 360 * '4.担保人-合并源数据'!D18 / '4.担保人-合并源数据'!D97) | D52: =IF('4.担保人-合并源数据'!E97=0, 0, 360 * '4.担保人-合并源数据'!E18 / '4.担保人-合并源数据'!E97) | E52: =IF('4.担保人-合并源数据'!F97=0, 0, 360 * '4.担保人-合并源数据'!F18 / '4.担保人-合并源数据'!F97) | F52: =IF('4.担保人-合并源数据'!G97=0, 0, 360 * '4.担保人-合并源数据'!G18 / '4.担保人-合并源数据'!G97) | G52: =IF('5.担保人-本部源数据'!D97=0, 0, 360 * '5.担保人-本部源数据'!D18 / '5.担保人-本部源数据'!D97) | H52: =IF('5.担保人-本部源数据'!E97=0, 0, 360 * '5.担保人-本部源数据'!E18 / '5.担保人-本部源数据'!E97) | I52: =IF('5.担保人-本部源数据'!F97=0, 0, 360 * '5.担保人-本部源数据'!F18 / '5.担保人-本部源数据'!F97) | J52: =IF('5.担保人-本部源数据'!G97=0, 0, 360 * '5.担保人-本部源数据'!G18 / '5.担保人-本部源数据'!G97)
A53: 偿债能力 | B53: 资产负债率 | C53: =IF('4.担保人-合并源数据'!D43=0, 0, '4.担保人-合并源数据'!D75 / '4.担保人-合并源数据'!D43) | D53: =IF('4.担保人-合并源数据'!E43=0, 0, '4.担保人-合并源数据'!E75 / '4.担保人-合并源数据'!E43) | E53: =IF('4.担保人-合并源数据'!F43=0, 0, '4.担保人-合并源数据'!F75 / '4.担保人-合并源数据'!F43) | F53: =IF('4.担保人-合并源数据'!G43=0, 0, '4.担保人-合并源数据'!G75 / '4.担保人-合并源数据'!G43) | G53: =IF('5.担保人-本部源数据'!D43=0, 0, '5.担保人-本部源数据'!D75 / '5.担保人-本部源数据'!D43) | H53: =IF('5.担保人-本部源数据'!E43=0, 0, '5.担保人-本部源数据'!E75 / '5.担保人-本部源数据'!E43) | I53: =IF('5.担保人-本部源数据'!F43=0, 0, '5.担保人-本部源数据'!F75 / '5.担保人-本部源数据'!F43) | J53: =IF('5.担保人-本部源数据'!G43=0, 0, '5.担保人-本部源数据'!G75 / '5.担保人-本部源数据'!G43)
B54: 现金短期有息债务比率 | C54: =IF(('4.担保人-合并源数据'!D45 + '4.担保人-合并源数据'!D50 + '4.担保人-合并源数据'!D61)=0, 0, '4.担保人-合并源数据'!D3 / ('4.担保人-合并源数据'!D45 + '4.担保人-合并源数据'!D50 + '4.担保人-合并源数据'!D61)) | D54: =IF(('4.担保人-合并源数据'!E45 + '4.担保人-合并源数据'!E50 + '4.担保人-合并源数据'!E61)=0, 0, '4.担保人-合并源数据'!E3 / ('4.担保人-合并源数据'!E45 + '4.担保人-合并源数据'!E50 + '4.担保人-合并源数据'!E61)) | E54: =IF(('4.担保人-合并源数据'!F45 + '4.担保人-合并源数据'!F50 + '4.担保人-合并源数据'!F61)=0, 0, '4.担保人-合并源数据'!F3 / ('4.担保人-合并源数据'!F45 + '4.担保人-合并源数据'!F50 + '4.担保人-合并源数据'!F61)) | F54: =IF(('4.担保人-合并源数据'!G45 + '4.担保人-合并源数据'!G50 + '4.担保人-合并源数据'!G61)=0, 0, '4.担保人-合并源数据'!G3 / ('4.担保人-合并源数据'!G45 + '4.担保人-合并源数据'!G50 + '4.担保人-合并源数据'!G61)) | G54: =IF(('5.担保人-本部源数据'!D45 + '5.担保人-本部源数据'!D50 + '5.担保人-本部源数据'!D61)=0, 0, '5.担保人-本部源数据'!D3 / ('5.担保人-本部源数据'!D45 + '5.担保人-本部源数据'!D50 + '5.担保人-本部源数据'!D61)) | H54: =IF(('5.担保人-本部源数据'!E45 + '5.担保人-本部源数据'!E50 + '5.担保人-本部源数据'!E61)=0, 0, '5.担保人-本部源数据'!E3 / ('5.担保人-本部源数据'!E45 + '5.担保人-本部源数据'!E50 + '5.担保人-本部源数据'!E61)) | I54: =IF(('5.担保人-本部源数据'!F45 + '5.担保人-本部源数据'!F50 + '5.担保人-本部源数据'!F61)=0, 0, '5.担保人-本部源数据'!F3 / ('5.担保人-本部源数据'!F45 + '5.担保人-本部源数据'!F50 + '5.担保人-本部源数据'!F61)) | J54: =IF(('5.担保人-本部源数据'!G45 + '5.担保人-本部源数据'!G50 + '5.担保人-本部源数据'!G61)=0, 0, '5.担保人-本部源数据'!G3 / ('5.担保人-本部源数据'!G45 + '5.担保人-本部源数据'!G50 + '5.担保人-本部源数据'!G61))
B55: 付现利息 | C55: ='4.担保人-合并源数据'!D165/10000 | D55: ='4.担保人-合并源数据'!E165/10000 | E55: ='4.担保人-合并源数据'!F165/10000 | F55: ='4.担保人-合并源数据'!G165/10000 | G55: ='5.担保人-本部源数据'!D165/10000 | H55: ='5.担保人-本部源数据'!E165/10000 | I55: ='5.担保人-本部源数据'!F165/10000 | J55: ='5.担保人-本部源数据'!G165/10000
B56: 其中：计入利润表的财务费用 | C56: ='4.担保人-合并源数据'!D104/10000 | D56: ='4.担保人-合并源数据'!E104/10000 | E56: ='4.担保人-合并源数据'!F104/10000 | F56: ='4.担保人-合并源数据'!G104/10000 | G56: ='5.担保人-本部源数据'!D104/10000 | H56: ='5.担保人-本部源数据'!E104/10000 | I56: ='5.担保人-本部源数据'!F104/10000 | J56: ='5.担保人-本部源数据'!G104/10000
B57: EBIT利息倍数 | C57: =IF('4.担保人-合并源数据'!D104=0, "-", ('4.担保人-合并源数据'!D118 + '4.担保人-合并源数据'!D104) / '4.担保人-合并源数据'!D104) | D57: =IF('4.担保人-合并源数据'!E104=0, "-", ('4.担保人-合并源数据'!E118 + '4.担保人-合并源数据'!E104) / '4.担保人-合并源数据'!E104) | E57: =IF('4.担保人-合并源数据'!F104=0, "-", ('4.担保人-合并源数据'!F118 + '4.担保人-合并源数据'!F104) / '4.担保人-合并源数据'!F104) | F57: =IF('4.担保人-合并源数据'!G104=0, "-", ('4.担保人-合并源数据'!G118 + '4.担保人-合并源数据'!G104) / '4.担保人-合并源数据'!G104) | G57: =IF('5.担保人-本部源数据'!D104=0, "-", ('5.担保人-本部源数据'!D118 + '5.担保人-本部源数据'!D104) / '5.担保人-本部源数据'!D104) | H57: =IF('5.担保人-本部源数据'!E104=0, "-", ('5.担保人-本部源数据'!E118 + '5.担保人-本部源数据'!E104) / '5.担保人-本部源数据'!E104) | I57: =IF('5.担保人-本部源数据'!F104=0, "-", ('5.担保人-本部源数据'!F118 + '5.担保人-本部源数据'!F104) / '5.担保人-本部源数据'!F104) | J57: =IF('5.担保人-本部源数据'!G104=0, "-", ('5.担保人-本部源数据'!G118 + '5.担保人-本部源数据'!G104) / '5.担保人-本部源数据'!G104)
B58: EBITDA利息倍数 | C58: =IF('4.担保人-合并源数据'!D104=0, "-", ('4.担保人-合并源数据'!D118 + '4.担保人-合并源数据'!D104 + C15 + C18 + C20) / '4.担保人-合并源数据'!D104) | D58: =IF('4.担保人-合并源数据'!E104=0, "-", ('4.担保人-合并源数据'!E118 + '4.担保人-合并源数据'!E104 + D15 + D18 + D20) / '4.担保人-合并源数据'!E104) | E58: =IF('4.担保人-合并源数据'!F104=0, "-", ('4.担保人-合并源数据'!F118 + '4.担保人-合并源数据'!F104 + E15 + E18 + E20) / '4.担保人-合并源数据'!F104) | F58: =IF('4.担保人-合并源数据'!G104=0, "-", ('4.担保人-合并源数据'!G118 + '4.担保人-合并源数据'!G104 + F15 + F18 + F20) / '4.担保人-合并源数据'!G104) | G58: =IF('5.担保人-本部源数据'!D104=0, "-", ('5.担保人-本部源数据'!D118 + '5.担保人-本部源数据'!D104 + G15 + G18 + G20) / '5.担保人-本部源数据'!D104) | H58: =IF('5.担保人-本部源数据'!E104=0, "-", ('5.担保人-本部源数据'!E118 + '5.担保人-本部源数据'!E104 + H15 + H18 + H20) / '5.担保人-本部源数据'!E104) | I58: =IF('5.担保人-本部源数据'!F104=0, "-", ('5.担保人-本部源数据'!F118 + '5.担保人-本部源数据'!F104 + I15 + I18 + I20) / '5.担保人-本部源数据'!F104) | J58: =IF('5.担保人-本部源数据'!G104=0, "-", ('5.担保人-本部源数据'!G118 + '5.担保人-本部源数据'!G104 + J15 + J18 + J20) / '5.担保人-本部源数据'!G104)
B59: 经营净现金流利息保障倍数 | C59: =IF('4.担保人-合并源数据'!D104=0, "-", '4.担保人-合并源数据'!D142 / '4.担保人-合并源数据'!D104) | D59: =IF('4.担保人-合并源数据'!E104=0, "-", '4.担保人-合并源数据'!E142 / '4.担保人-合并源数据'!E104) | E59: =IF('4.担保人-合并源数据'!F104=0, "-", '4.担保人-合并源数据'!F142 / '4.担保人-合并源数据'!F104) | F59: =IF('4.担保人-合并源数据'!G104=0, "-", '4.担保人-合并源数据'!G142 / '4.担保人-合并源数据'!G104) | G59: =IF('5.担保人-本部源数据'!D104=0, "-", '5.担保人-本部源数据'!D142 / '5.担保人-本部源数据'!D104) | H59: =IF('5.担保人-本部源数据'!E104=0, "-", '5.担保人-本部源数据'!E142 / '5.担保人-本部源数据'!E104) | I59: =IF('5.担保人-本部源数据'!F104=0, "-", '5.担保人-本部源数据'!F142 / '5.担保人-本部源数据'!F104) | J59: =IF('5.担保人-本部源数据'!G104=0, "-", '5.担保人-本部源数据'!G142 / '5.担保人-本部源数据'!G104)
A60: 现金流 | B60: 经营活动净现金流量 | C60: ='4.担保人-合并源数据'!D142/10000 | D60: ='4.担保人-合并源数据'!E142/10000 | E60: ='4.担保人-合并源数据'!F142/10000 | F60: ='4.担保人-合并源数据'!G142/10000 | G60: ='5.担保人-本部源数据'!D142/10000 | H60: ='5.担保人-本部源数据'!E142/10000 | I60: ='5.担保人-本部源数据'!F142/10000 | J60: ='5.担保人-本部源数据'!G142/10000
B61: 其中，销售商品提供劳务收到的现金 | C61: ='4.担保人-合并源数据'!D127/10000 | D61: ='4.担保人-合并源数据'!E127/10000 | E61: ='4.担保人-合并源数据'!F127/10000 | F61: ='4.担保人-合并源数据'!G127/10000 | G61: ='5.担保人-本部源数据'!D127/10000 | H61: ='5.担保人-本部源数据'!E127/10000 | I61: ='5.担保人-本部源数据'!F127/10000 | J61: ='5.担保人-本部源数据'!G127/10000
B62: 收现比 | C62: =IF('4.担保人-合并源数据'!D94=0, 0, '4.担保人-合并源数据'!D127 / '4.担保人-合并源数据'!D94) | D62: =IF('4.担保人-合并源数据'!E94=0, 0, '4.担保人-合并源数据'!E127 / '4.担保人-合并源数据'!E94) | E62: =IF('4.担保人-合并源数据'!F94=0, 0, '4.担保人-合并源数据'!F127 / '4.担保人-合并源数据'!F94) | F62: =IF('4.担保人-合并源数据'!G94=0, 0, '4.担保人-合并源数据'!G127 / '4.担保人-合并源数据'!G94) | G62: =IF('5.担保人-本部源数据'!D94=0, 0, '5.担保人-本部源数据'!D127 / '5.担保人-本部源数据'!D94) | H62: =IF('5.担保人-本部源数据'!E94=0, 0, '5.担保人-本部源数据'!E127 / '5.担保人-本部源数据'!E94) | I62: =IF('5.担保人-本部源数据'!F94=0, 0, '5.担保人-本部源数据'!F127 / '5.担保人-本部源数据'!F94) | J62: =IF('5.担保人-本部源数据'!G94=0, 0, '5.担保人-本部源数据'!G127 / '5.担保人-本部源数据'!G94)
B63: 投资活动净现金流 | C63: ='4.担保人-合并源数据'!D156/10000 | D63: ='4.担保人-合并源数据'!E156/10000 | E63: ='4.担保人-合并源数据'!F156/10000 | F63: ='4.担保人-合并源数据'!G156/10000 | G63: ='5.担保人-本部源数据'!D156/10000 | H63: ='5.担保人-本部源数据'!E156/10000 | I63: ='5.担保人-本部源数据'!F156/10000 | J63: ='5.担保人-本部源数据'!G156/10000
B64: 筹资活动净现金流 | C64: ='4.担保人-合并源数据'!D169/10000 | D64: ='4.担保人-合并源数据'!E169/10000 | E64: ='4.担保人-合并源数据'!F169/10000 | F64: ='4.担保人-合并源数据'!G169/10000 | G64: ='5.担保人-本部源数据'!D169/10000 | H64: ='5.担保人-本部源数据'!E169/10000 | I64: ='5.担保人-本部源数据'!F169/10000 | J64: ='5.担保人-本部源数据'!G169/10000
B65: 净现金流 | C65: ='4.担保人-合并源数据'!D171/10000 | D65: ='4.担保人-合并源数据'!E171/10000 | E65: ='4.担保人-合并源数据'!F171/10000 | F65: ='4.担保人-合并源数据'!G171/10000 | G65: ='5.担保人-本部源数据'!D171/10000 | H65: ='5.担保人-本部源数据'!E171/10000 | I65: ='5.担保人-本部源数据'!F171/10000 | J65: ='5.担保人-本部源数据'!G171/10000
